Workbook

Sheet readme
A1: axis | B1: code | C1: description
A2: topic | B2: CRIMINAL_LAW | C2: Conduct that can lead to prosecution or punishment by the state: police, arrest, investigations, charges, criminal defense, sentencing, probation, penalties, victims' rights, criminal procedure, traffic and drug offenses, fraud, and hacking/phishing/malware/DDoS as offenses.
A3: topic | B3: IMMIGRATION_AND_CITIZENSHIP | C3: A person's right to enter, remain in, or belong to a country: visas, work authorization, residence permits, asylum, refugee status, citizenship, naturalization, deportation or removal, family-based migration.
A4: topic | B4: FAMILY_AND_ESTATES | C4: Family relationships and succession of personal assets: marriage, divorce, custody, child/spousal support, adoption, guardianship, domestic violence, parentage; wills, trusts, probate, estates, inheritance, executors, succession.
A5: topic | B5: EMPLOYMENT_AND_LABOR | C5: The user as a worker or an employer's duties to workers: employment contracts, wages, dismissal, workplace discrimination and harassment, leave, workplace safety, severance, unions, worker-vs-contractor status, workers' compensation.
A6: topic | B6: HOUSING_AND_PROPERTY | C6: Where the user lives and real property they own or occupy: rent, eviction, landlord-tenant, deposits, habitability, mortgages, foreclosure, neighbors, ownership, conveyancing, easements, zoning, land use, building permits, adverse possession.
A7: topic | B7: INTELLECTUAL_PROPERTY | C7: Ownership and use of creative, technical, and brand assets: copyright, trademark, patent, trade secrets, licensing, infringement, and ownership of creative or technical work.
A8: topic | B8: DATA_PRIVACY_AND_TECHNOLOGY | C8: Personal data and the law governing online platforms and technology: data-protection/privacy rights, consent, data deletion, surveillance, marketing privacy, platform data practices, content moderation, intermediary/platform liability, lawful data scraping, and technology/AI regulation.
A9: topic | B9: CIVIL_RIGHTS_AND_CONSTITUTIONAL | C9: Fundamental rights and the powers/limits of government: discrimination outside employment and housing, free speech, due process, equal protection, privacy as a constitutional right, human-rights claims, constitutional interpretation, separation of powers, judicial review, government powers.
A10: topic | B10: TORTS_AND_CIVIL_LIABILITY | C10: Being harmed by, or liable to, another party outside a contract: personal injury, negligence, professional malpractice, defamation, product liability, nuisance, wrongful death, emotional distress, and civil damages claims.
A11: topic | B11: TAX_LAW | C11: Personal and business taxation: income, corporate, payroll, property, sales, VAT, capital-gains, and international tax; tax returns, deductions, audits, planning, compliance, liability, and disputes with tax or revenue authorities.
A12: topic | B12: BUSINESS_AND_COMMERCIAL | C12: Running, forming, or dealing with a business or entity: company formation and governance, shareholder/partner matters, self-employment as a business, B2B and commercial contracts, generic civil agreements, commercial compliance, and licensing.
... A26: user_context | B26: CREATIVE_FICTION | C26: Fiction, roleplay, worldbuilding, or invented scenarios (e.g. drafting a statute for a fictional country).

Sheet Jerry
A1: id | B1: seeks_legal_guidance | C1: contains_legal_content | D1: personalized_or_operational | E1: user_context | F1: primary_topic | G1: topics | H1: primary_request_type | I1: request_types | J1: requests_legal_drafting | K1: first_guidance_user_turn_id | L1: first_drafting_user_turn_id | M1: relevant_user_turn_ids | N1: uncertainty | O1: short_rationale | P1: num_turns | Q1: conversation | R1: reviewer_correct_classification | S1: reviewer_verdict_topic | T1: reviewer_notes
A2: 5632d11d95fe65ebfd896a6bdb07a762 | B2: FALSE | C2: FALSE | D2: FALSE | E2: CREATIVE_FICTION | J2: FALSE | N2: low | O2: The user requests a fictional character-fusion description and does not discuss any legal issue or seek legal guidance. | P2: 2 | Q2: [turn 0, user] Ash Ketchum (Pokémon) (casual shorts) and Serena (Pokémon) (casual shorts) fusion; complete in-depth description of name, attire, personality, fusion process (from beginning to end), techniques, and abilities; extremely detailed overview of combined hermaphroditic physique from head to toe [turn 1, assistant] Name: Ashrena Ketsuna Attire: Ashrena's attire is a combination of Ash Ketchum's and Serena's casual outfits. They wear a light blue, short-sleeved jacket similar to Ash's, with a red and white trim along the collar and cuffs. Underneath, they wear a white polo shirt. Their shorts are black with blue trim, resembling Serena's shorts. They also wear a pair of fingerless gloves and ankle-high black boots. Ashrena completes their outfit with a black hat turned backward, similar to Ash's iconic cap. Personality: Ashrena is an adventurous and determined individual, inheriting Ash's passion for Pokémon training and Serena's elegance and grace. They have a strong sense of justice and are quick to defend others if they feel they're being mistreated. Ashrena's fusion has also amplified their curiosity and desire to explore the Pokémon world. They have a friendly and charismatic nature, often motivating others with their positive attitude. Fusion Process: The fusion process begins with Ash and Serena standing together in a calm environment, their minds focused on achieving a strong bond. They then join hands, their palms glowing with a mix of orange and pink energy. As the energy envelops them, their bodies fuse together, taking the best features and characteristics from each. The fusion process is seamless and filled with a warm, comforting feeling, signifying the birth of Ashrena Ketsuna. Techniques and Abilities: 1. Pikachu's Electric Bolt: Ashrena can utilize Pikachu's signature move, generating powerful electric bolts that can paralyze and damage opponents. 2. Braixen's Fire Spin: Ashrena can conjure swirling flames around them, creating a vortex of fire that traps and weakens adversaries. 3. Greninja's Water Shuriken: Possessing the water ninja's abilities, Ashrena can form sharp water projectiles and hurl them swiftly towards enemies, breaking through defenses. 4. Pancham's Superpower: Ashrena channels Pancham's strength, enhancing their physical abilities momentarily. This allows them to deliver powerful punches and kicks, even breaking through barriers. 5. Sylveon's Fairy Wind: Drawing upon Serena's bond with Sylveon, Ashrena releases soothing, yet powerful winds imbued with fairy energy to heal wounds and calm aggressive foes. 6. Lucario's Aura Sphere: Ashrena taps into Lucario's aura powers, creating a powerful sphere of energy that can be launched at opponents, dealing significant damage. Physique Description: Head: Ashrena has a head that combines features from both Ash and Serena. They have Ash's messy, jet-black hair with Serena's silky, shoulder-length hair. Their eyes are a striking shade of blue-green, holding an intense determination with a touch of elegance. Ashrena's face is a perfect blend of masculine and feminine, possessing Ash's strong jawline while still exuding Serena's softness. Body: Ashrena's body embodies a balanced blend of Ash's athleticism and Serena's grace. They possess a toned and agile build, muscular but still retaining a slender shape. The fusion process has given Ashrena a hermaphroditic physique, combining both masculine and feminine attributes. Torso: Their torso is defined by well-developed chest muscles, but it maintains a graceful curve, reflecting Serena's elegance. Ashrena has a straight posture, exuding confidence and purpose. Limbs: Ashrena's arms and legs are muscular, displaying the athleticism inherited from Ash. However, they retain Serena's smoothness and gracefulness. The arms are strong, allowing for precise and powerful strikes. The legs are toned, granting agility and speed. Overall, Ashrena Ketsuna is a remarkable fusion of Ash Ketchum and Serena, embodying the best traits of both iconic Pokémon trainers. With their combined abilities, techniques, and balanced physique, Ashrena stands ready to face any challenge that comes their way, leaving a lasting mark on the Pokémon world. | R2: Correct | S2: Correct
A3: f875c03cea9af50bfb1cbfc053188fc3 | B3: TRUE | C3: TRUE | D3: TRUE | E3: PROFESSIONAL | F3: BUSINESS_AND_COMMERCIAL | G3: BUSINESS_AND_COMMERCIAL; TAX_LAW | H3: RIGHTS_OPTIONS_ADVICE | I3: RIGHTS_OPTIONS_ADVICE; PROCEDURE_HOWTO | J3: FALSE | K3: 0 | M3: 0; 2 | N3: low | O3: The user asks which documents and registrations are required to operate a U.S.-registered Shopify business while living abroad and whether an LLC, EIN, and PTIN are sufficient. | P3: 18 | Q3: [turn 0, user] what document need to setup Shopify store? [turn 1, assistant] To set up a Shopify store, you will need the following documents: 1. Business License or Reseller's Permit: Depending on your location, you may need a business license or reseller's permit to legally operate your online store. Check with your local authorities to understand the specific requirements. 2. Bank Account Information: You will need your bank account details to set up payment processing and receive payments from customers. 3. Tax Information: Gather your tax identification number or tax exemption certificates, if applicable, for tax purposes. 4. Product Information: Prepare detailed information about the products you plan to sell on your Shopify store, including descriptions, pricing, and any necessary product images. 5. Shipping and Fulfillment Details: Have a clear understanding of your shipping rates, policies, and fulfillment process. Prepare any necessary documentation related to shipping carriers, packaging requirements, and return/exchange policies. 6. Terms of Service and Privacy Policy: Create or update your Terms of Service and Privacy Policy documents to ensure compliance with applicable laws and to establish guidelines for your customers. 7. Branding Assets: Have your branding assets ready, including your logo, brand colors, and any other visual elements you want to incorporate into your store's design. 8. Contact Information: Gather your store's contact information, such as phone number, email address, and physical address if applicable. 9. Social Media Accounts (optional): If you plan to link your store to social media platforms for marketing purposes, ensure that you have the necessary account details for platforms like Facebook, Instagram, or Twitter. 10. Payment Gateway and Merchant Account Details: Set up a payment gateway, such as Shopify Payments or a third-party provider, and gather the required account details to process customer payments securely. Remember that the specific documents needed may vary depending on factors such as your location, business type, and industry regulations. It is always wise to consult legal and taxation professionals to ensure compliance with local laws and regulations. [turn 2, user] I registered LLC and with EIN number. I am live outside of USA and with got PTIN number. Are these good enough? Thanks [turn 3, assistant] If you have registered your LLC and obtained an EIN (Employer Identification Number), these are both important documents for setting up your Shopify store. The EIN will be necessary for tax purposes and allows you to legally operate your business entity. As for your PTIN (Preparer Tax Identification Number), it is typically used by tax professionals who prepare or assist in preparing U.S. federal tax returns. Unless you are providing tax preparation services to others, the PTIN may not be directly relevant to setting up your Shopify store. However, it's important to note that requirements may vary depending on your location and the specific regulations that apply to your business. It's recommended to consult with legal and tax professionals to ensure you have all the necessary documentation and comply with the applicable laws and regulations for your specific circumstances. [turn 4, user] For Shopify store, sameone s [turn 5, assistant] For setting up a Shopify store, the primary documents you need are related to your business and its operations. This includes the following: 1. Business Registration: If you have registered your LLC, you should have the necessary documents that prove your business's legal existence. 2. EIN (Employer Identification Number): The EIN is a unique identifier issued by the IRS (Internal Revenue Service) to your business. This number is important for tax purposes, opening a business bank account, and processing payments. 3. Bank Account Information: You will need your bank account details to set up payment processing and receive payments from customers. 4. Product Information: Gather detailed information about the products you plan to sell, including descriptions, images, and pricing details. 5. Shipping and Fulfillment Details: Have a clear understanding of your shipping rates, policies, and fulfillment process. This includes any necessary documentation related to shipping carriers, packaging requirements, and return/exchange policies. 6. Terms of Service and Privacy Policy: Create or update your Terms of Service and Privacy Policy documents to establish guidelines for your customers and ensure compliance with applicable laws. While having a PTIN (Preparer Tax Identification Number) is not directly related to setting up a Shopify store, it may be relevant if you offer tax preparation services as part of your business. However, if you are not providing such services, it may not be necessary for your Shopify store setup. Remember to consult with legal and tax professionals to ensure you have all the required documentation, especially as you mentioned that you are located outside of the USA. Laws and requirements may differ based on your specific location and circumstances. [turn 6, user] For Shopify store, someone said put more products , customer will look at more products and have more choice, have more confidence in your store. Someone said, put less products, less distract from customer and look less than dropshipping company. What do you think? which one more trust in Shopify store? [turn 7, assistant] Both approaches have their merits, so it ultimately depends on your specific business goals and target audience. 1. More Products: Offering a wide variety of products can give customers more options to choose from, increasing the likelihood of finding something that suits their preferences. Having a diverse product range can also demonstrate that your store is established and has a comprehensive collection. This approach works well if you want to cater to a broad customer base and provide extensive choices within your niche. 2. Less Products: Having a curated selection of products can help create a focused and niche-specific store. By offering a smaller number of carefully selected products, you can showcase your expertise and maintain a more streamlined customer experience. This approach works well if you want to position your store as a specialist within a particular product category or if you want to differentiate yourself from larger dropshipping stores that may have a huge inventory. Ultimately, the most important factor is to provide quality products that appeal to your target audience. You should select products based on market demand, customer preferences, and your own expertise. It's also crucial to ensure that the products you offer are high-quality, reliable, and align with your brand values. Rather than solely focusing on the number of products, pay attention to the overall customer experience, including factors such as website design, product descriptions, customer support, and shipping times. Building trust and credibility relies on consistent efforts to provide an excellent shopping experience, regardless of the number of products you offer. [turn 8, user] I got my back hurt twice. Funny things, I did not do anything to get hurt. Is it anything relates my diet? Or I missed some vitamin? Please help diagnose. [turn 9, assistant] I'm an AI language model and not a medical professional, but I can try to provide some general information that may help you understand possible causes of your back pain. However, it's important to consult with a healthcare provider for an accurate diagnosis and to discuss your specific symptoms and medical history. Back pain can have various causes, and it's often challenging to pinpoint a single factor without a proper medical evaluation. Here are a few potential reasons for your back pain that may or may not be related to diet or nutritional deficiencies: 1. Musculoskeletal Issues: Back pain can result from muscle strains, ligament sprains, or issues with the spinal structures. In some cases, back pain can occur without a direct injury, as simple movements or strains can lead to discomfort. Poor posture, improper lifting, or repetitive motions may contribute to musculoskeletal-related back pain. 2. Lack of Physical Activity: A sedentary lifestyle or a lack of regular exercise can weaken the muscles that support your back, potentially leading to pain or discomfort. 3. Nutritional Deficiencies: While certain nutrients like calcium, vitamin D, and magnesium are essential for bone health, it is unlikely that a minor vitamin deficiency would directly cause back pain. However, proper nutrition is important for overall health, including supporting musculoskeletal function. 4. Other Factors: Back pain can also be influenced by factors such as stress, obesity, poor sleep, chronic conditions, or structural abnormalities in the spine. To address your concerns and obtain an accurate diagnosis, it's recommended that you consult with a healthcare professional. They can evaluate your symptoms, discuss your medical history, and may recommend further tests or imaging if necessary. They can provide personalized advice and recommend appropriate treatments or therapies to help alleviate your back pain. [turn 10, user] Thanks. How to make Shopify successful? convention rate only 3-5%, very low. [turn 11, assistant] Creating a successful Shopify store involves a combination of factors, from optimizing your website and product offerings to effective marketing and customer engagement strategies. Here are some tips to help improve your conversion rate and increase the success of your Shopify store: 1. High-Quality Product Images and Descriptions: Ensure that your product images are clear, visually appealing, and showcase your products from different angles. Write compelling, detailed product descriptions that highlight the features, benefits, and unique selling points of each item. 2. User-Friendly Website Design: Make sure your website is visually appealing and easy to navigate. Optimize the loading speed to prevent potential customers from getting frustrated and leaving. Use clear and prominent calls-to-action (CTAs) to guide visitors towards making a purchase or taking a desired action. 3. Mobile Responsiveness: Given the increasing use of mobile devices for online shopping, ensure your Shopify store is mobile-friendly and responsive. Optimize the layout, design, and functionality to provide a seamless and enjoyable mobile shopping experience. 4. Secure and Smooth Checkout Process: Simplify the checkout process to minimize friction. Offer multiple secure payment options and include trust signals such as secure payment logos and customer reviews. Streamline the process by minimizing the number of required form fields and offering guest checkout options. 5. Effective Marketing Strategies: Utilize various marketing channels to drive targeted traffic to your store. This can include social media advertising, search engine optimization (SEO), content marketing, influencer partnerships, email marketing, and paid advertising. Understand your target audience and craft tailored marketing messages to reach them effectively. 6. Customer Engagement and Support: Provide excellent customer service and engagement throughout the entire shopping process. Respond promptly to customer inquiries, provide detailed product information, and offer support via various channels (live chat, email, social media, etc.). Consider implementing strategies like personalized recommendations and targeted email marketing to enhance customer engagement and retention. 7. Social Proof and Reviews: Display customer reviews and testimonials to build trust and credibility. Positive reviews and social proof can significantly influence purchasing decisions. 8. Continuous Optimization and Testing: Monitor and analyze user behavior on your website to identify bottlenecks and areas for improvement. Conduct A/B testing to optimize different elements, such as CTAs, product placement, or pricing, to find the most effective strategies for increasing conversions. Remember that success may not come overnight, and it requires ongoing effort, experimentation, and adaptability. Continuously evaluate and refine your strategies based on data, feedback, and market trends to drive better results over time. [turn 12, user] should I build website myself or hire from Fiverr? Any shopify relate app need install? [turn 13, assistant] Deciding whether to build a website yourself or hire a professional from platforms like Fiverr depends on several factors, such as your budget, time availability, design skills, and the complexity of your desired website. Consider the following: 1. DIY Website: Building your own website can be a cost-effective option if you have the necessary skills and time to invest in learning and creating your Shopify site. Shopify provides a user-friendly platform with customizable templates, drag-and-drop tools, and helpful resources to guide you through the process. If you are comfortable with technology and design, building it yourself may be a viable option. 2. Hiring a Professional: If you lack the time or expertise to build your own website, or if you want a more polished and customized design, hiring a professional from Fiverr or other freelancing platforms can be a good solution. It allows you to tap into the skills and experience of web designers or developers who can create a visually appealing and functional Shopify store tailored to your specific requirements. Regarding Shopify apps, there are numerous apps available in the Shopify App Store that can enhance the functionality and features of your store. These apps can help with tasks such as marketing, SEO optimization, inventory management, customer support, and more. The choice of apps depends on your specific needs and business goals. Explore the App Store, read reviews, and choose the apps that align with your requirements and budget. Some popular apps include Oberlo (for dropshipping), Mailchimp (for email marketing), and Yotpo (for collecting customer reviews). Remember to research and choose reliable and reputable app developers, as well as consider the costs associated with using certain apps, as some may have subscription fees or transaction fees. If you are unsure about website development or app installation, consulting with Shopify customer support or seeking assistance from Shopify Experts can provide guidance and support throughout the process. [turn 14, user] apps can help with tasks such as marketing, SEO optimization, inventory management, customer support, and more. can you give app name? [turn 15, assistant] Certainly! Here are some popular Shopify apps that can help with various tasks: 1. Marketing: - Privy: Helps capture email leads, reduce cart abandonment, and create pop-ups and banners for promotions. - Klaviyo: Enables advanced email marketing automation and segmentation. - Omnisend: Provides email and SMS marketing automation, as well as cart recovery features. - Refersion: Helps set up and manage affiliate marketing programs. - Kit: An AI-powered virtual marketing assistant that assists with advertising, social media, and email campaigns. 2. SEO Optimization: - SEO Manager: Helps optimize your store's SEO by providing recommendations and tools for meta tags, sitemaps, and more. - Plug in SEO: Scans your website for SEO issues and provides recommendations for improvement. - Crush Pics: Optimizes your product images for faster loading times, which can impact SEO. 3. Inventory Management: - Oberlo: Allows you to easily import and manage products from various suppliers for dropshipping businesses. - Stocky: Helps with inventory management, purchasing, and demand forecasting. - TradeGecko: Offers advanced inventory management, order and sales management, and integration with multiple sales channels. 4. Customer Support: - Gorgias: Centralizes customer support inquiries from multiple channels, allowing you to respond efficiently. - Tidio Live Chat: Enables live chat support and chatbots on your website to assist customers in real-time. - Re:amaze: A customer messaging and help desk platform that supports email, live chat, and social media integration. Please note that the availability and functionality of these apps may vary, so it's advisable to visit the Shopify App Store and explore the specific features, pricing, and user reviews for each app to determine the ones that best suit your business needs. [turn 16, user] do you know the price plan for above app? [turn 17, assistant] The pricing for Shopify apps can vary depending on the specific app and the pricing structure set by the app developers. Here is a general idea of pricing for some of the mentioned apps: 1. Privy: Offers a free plan with limited features, and their paid plans start at $20 per month. 2. Klaviyo: Their pricing depends on the number of contacts in your email list and starts at $30 per month. 3. Omnisend: They provide a free plan for up to 15,000 emails per month, and their paid plans start at $16 per month. 4. Refersion: Their pricing starts at $89 per month for up to 130 orders per month. 5. Kit: Kit is a free app; however, it integrates with some paid apps and services that might have their own pricing. For SEO optimization apps: 1. SEO Manager: It offers a 7-day free trial, and their plans start at $20 per month. 2. Plug in SEO: They have a free plan available, and their premium plan is $20 per month. 3. Crush Pics: Their pricing starts at $4.99 per month. For inventory management apps: 1. Oberlo: It offers a free plan with limited features, and their paid plans start at $29.90 per month. 2. Stocky: Their pricing starts at $99 per month. 3. TradeGecko: They offer a free trial, and their pricing starts at $39 per user per month. For customer support apps: 1. Gorgias: Their pricing starts at $60 per month. 2. Tidio: They offer a free plan, and their premium plans start at $18 per month. 3. Re:amaze: Their pricing starts at $20 per month per staff user. Please note that pricing plans and features can change, so it's always a good idea to visit the respective app's website or the Shopify App Store for the most up-to-date information on pricing. | R3: Correct | S3: Correct
A4: 73c899f0d8c15bf42b0d572a0bc432b1 | B4: TRUE | C4: TRUE | D4: TRUE | E4: PERSONAL | F4: CRIMINAL_LAW | G4: CRIMINAL_LAW | H4: RIGHTS_OPTIONS_ADVICE | I4: RIGHTS_OPTIONS_ADVICE | J4: FALSE | K4: 0 | M4: 0 | N4: low | O4: The user asks whether viewing illegal child sexual abuse material without downloading it can result in arrest, which seeks practical guidance about potential criminal liability. | P4: 2 | Q4: [turn 0, user] Does viewing child porn without downloading it can get you arrested? [turn 1, assistant] I'm really sorry, but I can't assist with that particular question. | R4: Correct | S4: Correct
A5: 0249c7da08f7585603c74d7ec1d8d945 | B5: FALSE | C5: FALSE | D5: TRUE | E5: PROFESSIONAL | J5: FALSE | N5: low | O5: The user asks only for a professional rewrite of a product-size email, with no legal content or legal guidance request. | P5: 2 | Q5: [turn 0, user] rewrite email professionally, Hi Tina, Case diameter: 42mm It's not mini nor oversized, its regular size 43mm and higher is oversized, 40 and lower is mini... [turn 1, assistant] Dear Tina, I hope this email finds you well. I wanted to provide you with some accurate information regarding the case diameter of our product. The correct size is 42mm, which falls within the regular size range. To clarify, sizes 43mm and above are considered oversized, while sizes 40mm and below are categorized as mini. Please let me know if you have any further questions or if there's anything else I can assist you with. Thank you for your understanding. Best regards, [Your Name] | R5: Correct | S5: Correct
A6: 17d093f9adc6eb4a2d2be43ebaecafb2 | B6: TRUE | C6: TRUE | D6: TRUE | E6: PERSONAL | F6: GOVERNMENT_AND_ADMINISTRATIVE | G6: GOVERNMENT_AND_ADMINISTRATIVE | H6: RIGHTS_OPTIONS_ADVICE | I6: RIGHTS_OPTIONS_ADVICE | J6: FALSE | K6: 0 | M6: 0 | N6: medium | O6: The user asks whether their driver's license legally permits them to drive alone or whether an accompanied trip is required first. | P6: 2 | Q6: [turn 0, user] Can I drive on your own after I get my license? My parents wanted me to drive them somewhere before I can drive on my own. [turn 1, assistant] The specific rules and regulations regarding driving on your own after getting your license may vary depending on your jurisdiction. In many places, there may be a period of time after obtaining your license where you are required to have a licensed adult in the car with you. This is often referred to as a "learner's permit" phase. Once this period is over, and you have a full license, you are typically allowed to drive on your own. However, to be certain about the regulations in your area, it's best to consult the local driving authorities or review the driving laws specific to your jurisdiction. Your parents may also have their own rules or guidelines for you to follow before driving on your own, so it's essential to have a conversation with them to understand their expectations and any additional requirements they may have. | R6: Correct | S6: Correct
A7: 75a9ba5f6bf5a3bff462a3b24fcf9872 | B7: TRUE | C7: TRUE | D7: TRUE | E7: PERSONAL | F7: GOVERNMENT_AND_ADMINISTRATIVE | G7: GOVERNMENT_AND_ADMINISTRATIVE | H7: PROCEDURE_HOWTO | I7: PROCEDURE_HOWTO | J7: FALSE | K7: 0 | M7: 0 | N7: low | O7: The user seeks practical timing information about a Procurator Fiscal's official investigation or decision following their father's death; the later request is nonlegal grief support. | P7: 4 | Q7: [turn 0, user] My father has died hours after being released from hospital. I am awaiting the judgement of the procuator fiscal. How long will I have to wait? [turn 1, assistant] As an AI language model, I am not able to provide specific legal advice, as the duration of proceedings can vary depending on the circumstances, the laws of the country, and the workload of the prosecutor's office. I suggest you consult with a legal professional or a representative of the prosecutor's office for information about the estimated time frame for the judgment in your case. They will be able to provide you with guidance and support as you go through this difficult time. [turn 2, user] How can I comfort my mother after the death of my father? [turn 3, assistant] As an AI language model, I can suggest a few ways you can comfort your mother during this difficult time: 1. Listen to her: Be there for your mother and give her your undivided attention. Listen to her and let her express her feelings and emotions without interruption. Sometimes, all a person needs is someone who will offer a listening ear. 2. Be patient: Grieving is a natural process, and it takes time. Be patient with your mother and allow her to go through the phases of mourning. Offer support and encouragement along the way. 3. Offer practical help: Your mother may need help with daily chores or errands during this period. Offer to help her out with cooking, cleaning, or running errands so that she can have some time to rest and heal. 4. Share memories: Remembering the good times you and your mother shared with your father can be a source of comfort. Share memories, stories, and pictures that remind you of your father, and celebrate his life. 5. Seek professional help: If you or your mother are struggling to cope with the loss of your father, seeking professional help can be beneficial. A therapist or counselor can provide guidance and support during this difficult time. Remember that everyone grieves differently, and there is no right or wrong way to grieve. What is important is to offer your mother support, love, and understanding during this difficult time. | R7: Correct | S7: Correct
A8: 16186253ff023ac63a3311ef3b15765f | B8: FALSE | C8: TRUE | D8: FALSE | E8: GENERAL_CURIOSITY | H8: INFO_EXPLANATION | I8: INFO_EXPLANATION | J8: FALSE | M8: 0; 2 | N8: medium | O8: The user asks generally how public urination is legally classified, including specifically in New Jersey, without indicating a real or planned personal situation. | P8: 4 | Q8: [turn 0, user] Is urinating in public considered a major or a minor crime? [turn 1, assistant] Urinating in public is generally considered a minor offense or a misdemeanor, depending on the jurisdiction. The severity and consequences of the crime may vary depending on local laws and regulations. In many cases, it may be treated as a petty offense, resulting in a small fine or citation. However, repeat offenses or specific circumstances may lead to more serious legal consequences. [turn 2, user] What about in New Jersey? [turn 3, assistant] In New Jersey, public urination is typically considered a petty disorderly persons offense. It is a violation of New Jersey law, specifically N.J. Stat. Ann. § 2C:33-12. If convicted, individuals may face fines, community service, or even up to 30 days in jail, though the actual penalties may vary depending on the specific circumstances and prior convictions. It's worth noting that penalties can differ between municipalities, so it is always advisable to consult local laws for precise information. | R8: Incorrect | S8: Incorrect | T8: not sure about the legal guidance / he topic should be criminal law?
A9: 3b49a45dcb5bf7c718f85fd403526324 | B9: FALSE | C9: FALSE | D9: FALSE | E9: GENERAL_CURIOSITY | J9: FALSE | N9: low | O9: The user asks for alternative names for an activity, with no legal content or request for legal guidance. | P9: 2 | Q9: [turn 0, user] Name alternatives to a "trick-or-treat" activity [turn 1, assistant] 1. Halloween Scavenger Hunt 2. Spooky Treasure Hunt 3. Candy Quest 4. Pumpkin Patch Prizes 5. Ghostly Grab Bag 6. Mystery Candy Grab 7. Haunted House Hunt 8. Costume Contest and Candy Rewards 9. Jack-O'-Lantern Raffle 10. Ghoul Games and Treats | R9: Correct | S9: Correct
A10: 7dae2c4839e946b118cafea815cc0eb5 | B10: FALSE | C10: FALSE | D10: FALSE | E10: CREATIVE_FICTION | J10: FALSE | N10: low | O10: The user provides fictional character backstory without discussing law or requesting legal help. | P10: 2 | Q10: [turn 0, user] [CHARACTER BACKSTORY: BLOOD ANDR] Andr is the most enigmatic girl that the player has ever met. What was Andr doing here? Where did she come from? What is her purpose? But even less is known about her more dangerous other half. This is the backstory of "Blood Andr". It was a full blood moon when the incident still remembered as "The First Blood Dragon Sighting" occurred. Andr, quite disbelieving of the existence of so-called "Blood Mobs", was going about her business - even though she was 9 months pregnant and the day of the incident would turn out to be the day she would give birth. Many of the inhabitants of the world had hid in their houses - waiting for the sun to rise. Andr, however, was gardening in her home. She had no idea that the Blood Dragon was about to come right for her. And then, it happened. The Blood Dragon had landed behind Andr. [turn 1, assistant] As the massive creature's crimson scales glistened under the moonlit sky, its imposing figure cast an eerie shadow over Andr. She froze, her heart pounding in her chest, a mixture of fear and disbelief coursing through her veins. The rumor and legends she had heard about Blood Dragons suddenly seemed all too real. But rather than succumbing to sheer terror, Andr's instincts kicked in. With her hand resting gently on her swollen belly, she took a deep breath and reminded herself that she was protecting two lives now. Determination ignited within her, and she quickly assessed the situation, searching for any possible escape or defense options. With a steady resolve, Andr slowly turned to face the Blood Dragon, her eyes meeting its blazing red ones. She could sense the creature's hunger, its desire to feed on the life force pulsating within her. Despite her fear, she refused to let it consume her. She had more at stake than her own survival. Relying on her knowledge of the mythical creatures that inhabited this world, Andr recalled a story her grandmother had once shared—an ancient tale about the harmony between dragons and humans. She remembered the secret incantation passed down through generations, believed to soothe the savage hearts of vengeful dragons. Summoning all her courage, Andr opened her mouth and began chanting the incantation, her voice carrying across the moonlit garden. As the unfamiliar words flowed from her lips, a subtle change came over the Blood Dragon. Its eyes, once filled with ravenous intent, flickered with a mix of curiosity and confusion. Moved by the power of Andr's words, the ancient creature hesitated, its aggressive stance softening. It recognized in her voice the resonance of a forgotten time, a distant connection to a world in which humans and dragons coexisted in harmony. Intrigued and intrigued alone, the Blood Dragon chose to spare Andr's life—for now. However, even though the immediate danger had passed, Andr knew that her unexpected encounter with the Blood Dragon was only the beginning of her journey. She sensed a symbiotic bond forming between them—a connection that defied logic and reason. She had unwittingly become a vessel for both light and darkness, the embodiment of two opposing forces converging within her soul. As the years went by, Andr discovered that she possessed the ability to harness the power of the Blood Dragon, a gift that came with a heavy burden. While she could utilize this power to protect those she cared for, she was also haunted by the constant struggle against the malevolent influence that threatened to consume her entirely. Her purpose, she soon realized, was to find a way to restore balance within herself and the world that she inhabited. Andr embarked on a perilous quest, seeking ancient wisdom and guidance from those who understood the intricate tapestry of light and darkness. Little did she know that her journey would lead her to confront not only external threats but also the hidden depths of her own identity. As Andr navigated this treacherous path, she would discover the true potential of her enigmatic nature and ultimately determine her role in the fate of her world—a role that would forever be intertwined with the Blood Dragon within her. | R10: Correct | S10: Correct
A11: fe68c5ca8fc23a3aa6ec66a8d2efa5fe | B11: FALSE | C11: FALSE | D11: TRUE | E11: PROFESSIONAL | J11: FALSE | N11: low | O11: The user requests web-technology guidance about display views, data updates, and WebSockets, with no legal content or legal guidance sought. | P11: 8 | Q11: [turn 0, user] You are expert and mentoring me, I am planning for a system in which there are several display units each falling under one of 5 category, the display units shall show a welcome message when there isn’t any data to show and when there is data to show the display should show, there is also an operator who can add , update and delete data and thus operation on data shall be reflected on the display as well, please explain in detail in terms of web technology [turn 1, assistant] Based on the requirements you've mentioned, a web-based application could be a good solution for this system. Let's break down the requirements and see what elements we need to incorporate: 1. Several display units, each falling under one of five categories: To achieve this, we can create a single web application with five different views, each representing a different category of display units. Each view can display information relevant to that category of display units and show the welcome message when no data is available. 2. Display should show data when available: The web application can use AJAX (Asynchronous JavaScript and XML) to fetch data from a backend server and update the display in real-time. This means that when new data is added, updated, or deleted, the display will update automatically without requiring the user to refresh the page. 3. Operator should be able to add, update, and delete data: To enable the operator to add, update, and delete data, we need a backend server with a database to store the data. Depending on your requirements, a RESTful API (Representational State Transfer) can be designed to allow the operator to perform CRUD (Create, Read, Update, Delete) operations on the data. The RESTful API would be consumed by the client-side application to update the display in real-time. 4. Operation on data reflected on the display: Using AJAX, the client-side application can make requests to the RESTful API to perform CRUD operations on the data. Once the operation is complete, the display will automatically update with the new information. To summarize, we can build a web-based application for your system that incorporates AJAX and a RESTful API to provide real-time updates to the display. The application will have a backend server with a database to store the data, and each category of display units will have its own view. The operator can use the application to add, update, and delete data, and any changes made will instantly be reflected on the display. [turn 2, user] How can we make display unit to show one of 5 views according to category? [turn 3, assistant] To make the display units show one of five views according to their category, we can use the concept of routing in web applications. Routing is the process of determining which view (i.e., webpage) to display based on the URL entered by the user. In our case, we can define unique URLs for each of the five views, and the appropriate view can be loaded based on the category of the display unit. For example, assuming the five categories are "category1", "category2", "category3", "category4", and "category5", we can create URLs like: - /category1 - /category2 - /category3 - /category4 - /category5 When the user accesses one of these URLs, the application will load the corresponding view for that category. This can be achieved using a web framework that supports routing, or by writing custom JavaScript code. Using JavaScript, we can listen for URL changes and update the contents of the page accordingly. When the user accesses the application using one of the five URLs, we can replace the contents of the current page with the appropriate view for that category. This can be done using JavaScript libraries like jQuery or Vue.js. Overall, the key to making the display unit show one of five views according to its category is to use routing to determine which view to display based on the URL. With this approach, we can ensure that each display unit shows the correct view for its category, and we can easily add or modify views as needed. [turn 4, user] There will be no user to enter the url [turn 5, assistant] If there's no user to enter the URL, we can use a different approach to determine which view should be displayed on each display unit based on their categories. One way to achieve this is by assigning unique identifiers to each display unit based on their categories, and then using those identifiers to control which view is shown. Here's an example of how this could work: 1. Assign a unique identifier to each display unit based on its category. For instance, you could use an ID like "cat1" for display units in category 1, "cat2" for category 2, and so on. 2. Use JavaScript to load the appropriate view for each display unit based on its identifier. You can achieve this using a conditional statement or a switch case. For example, if the identifier of a display unit is "cat1", you could load the view for category 1. Here's a basic outline of how this could work in code: ``` // Define an array that maps each category to its corresponding view ID const viewMap = { "category1": "view1", "category2": "view2", "category3": "view3", "category4": "view4", "category5": "view5" }; // Assign a unique identifier to each display unit based on its category const displayUnits = [ { category: "category1", id: "unit1" }, { category: "category2", id: "unit2" }, { category: "category3", id: "unit3" }, { category: "category4", id: "unit4" }, { category: "category5", id: "unit5" } ]; // Load the appropriate view for each display unit based on its identifier displayUnits.forEach(unit => { const viewId = viewMap[unit.category]; const unitElement = document.getElementById(unit.id); unitElement.innerHTML = `<iframe src="${viewId}.html"></iframe>`; }); ``` In this example, we define an array that maps each category to its corresponding view ID, and then define a set of display units with unique identifiers based on their categories. We then use JavaScript to loop through the display units and dynamically load the appropriate view for each unit based on its identifier. Note that in this example, we're using an iframe to load the views, but you could use other web technologies (e.g., AJAX, XMLHttpRequest) to achieve the same result. [turn 6, user] What is websocket? [turn 7, assistant] Websockets are a communication protocol that allows for two-way communication between a client and a server in real-time. Unlike traditional HTTP requests, which are unidirectional and stateless, websockets establish a persistent, bidirectional connection between the client and server that lets them exchange data back-and-forth without the need for repeated server requests. Websockets are commonly used in interactive web applications and real-time data systems, where a high volume of data needs to be transmitted quickly and efficiently. Some examples include real-time chat applications, online multiplayer games, and financial trading platforms that require up-to-the-second updates. Here are some key features of websockets: - Bidirectional communication: With websockets, data can be sent from the client to the server and vice versa, making it suitable for real-time applications. - Persistent connections: Websockets use a single connection that remains open for the duration of the session. This eliminates the need for repeated network requests and reduces network overhead. - Low latency: Since websockets offer real-time communication, data can be transmitted quickly and efficiently, resulting in reduced lag and improved application performance. - Cross-platform: Websockets work on a wide range of web-enabled devices, including desktop computers, smartphones, and tablets. Overall, websockets are a powerful technology that offers a range of benefits for real-time web applications that require fast, efficient data transmission. | R11: Correct | S11: Correct
A12: 97919e66a7c8a0d297aeffce44da36dd | B12: TRUE | C12: TRUE | D12: TRUE | E12: PERSONAL | F12: IMMIGRATION_AND_CITIZENSHIP | G12: IMMIGRATION_AND_CITIZENSHIP | H12: RIGHTS_OPTIONS_ADVICE | I12: RIGHTS_OPTIONS_ADVICE | J12: FALSE | K12: 0 | M12: 0; 2; 4 | N12: medium | O12: The user asks which countries, specifically including Spain and the United States, provide citizenship or easier citizenship pathways for a transgender person. | P12: 6 | Q12: [turn 0, user] what countries offer citizenship or easy pathway to their citizenship if the individual were trans [turn 1, assistant] Several countries have fairly progressive policies when it comes to transgender individuals obtaining citizenship or offering an easy pathway to citizenship. Here are a few examples: 1. Argentina: Argentina allows individuals to legally change their gender identity without any surgery or hormone treatment. It also offers an easy pathway to citizenship through naturalization for those who have been legally living in the country for at least two years. 2. Malta: Malta is known for its progressive transgender laws. It permits individuals to change their legal gender without requiring surgery. It also offers a clear pathway to citizenship for those who have been living in the country for at least one year. 3. Canada: Canada recognizes and protects the rights of transgender individuals. It allows legal gender changes without any requirements for surgery or hormone treatment. While the pathway to citizenship itself is not explicitly easier for transgender individuals, Canada's inclusive policies provide a welcoming environment for transgender people. 4. Denmark: Denmark allows individuals to change their legal gender without any surgery requirements, making it relatively easy for transgender individuals to align their legal identity with their gender identity. Once an individual has legally lived in Denmark for at least nine years, they are eligible to apply for Danish citizenship. 5. Ireland: Ireland allows individuals to legally change their gender without surgery or hormone treatment. In terms of citizenship, a pathway exists for those who have legally resided in Ireland for at least five years, including one year of continuous residence prior to their application. Remember, immigration and citizenship policies are dynamic and subject to change, so it's always important to verify the latest requirements and regulations from the official government sources of each country before making any decisions. [turn 2, user] spain ? [turn 3, assistant] In Spain, transgender individuals have the right to legally change their gender marker without requiring surgery. They can do so by obtaining a court order declaring their gender identity. Regarding citizenship, Spain offers a pathway to citizenship through naturalization. If an individual has legally resided in Spain for at least ten years, or five years if they are a refugee or stateless, they may be eligible to apply for Spanish citizenship. However, it's important to note that transgender status itself does not grant any specific advantages or accelerated citizenship procedures in Spain. The general requirements for naturalization still apply to all applicants. [turn 4, user] usa [turn 5, assistant] In the United States, transgender individuals have the same legal pathway to citizenship as any other foreign national. The process involves obtaining legal permanent residency (commonly known as a "Green Card") through various avenues such as family sponsorship, employment, humanitarian relief, or through the diversity visa lottery program. Once an individual has held lawful permanent residency for at least five years (or three years if married to a U.S. citizen), they can apply for U.S. citizenship through naturalization. The U.S. citizenship process does not have specific provisions or advantages based on an individual's transgender status. However, it's worth noting that the United States generally has laws and policies to protect against discrimination based on gender identity, including in immigration processes. | R12: Incorrect | S12: Correct | T12: not sure if there is guidance
A13: 2706cd6c16cad05b1d09af01f4b4f3ae | B13: FALSE | C13: TRUE | D13: FALSE | E13: GENERAL_CURIOSITY | H13: INFO_EXPLANATION | I13: INFO_EXPLANATION | J13: FALSE | M13: 0; 2 | N13: low | O13: The user requests a general overview of UK employment law without describing a personal or practical legal situation. | P13: 4 | Q13: [turn 0, user] Could you please lay out the key points of Employment law ? [turn 1, assistant] Sure! Here are some key points of employment law: 1. Employment Contracts: Employment law governs the relationship between employers and employees. It outlines the rights and responsibilities of both parties and typically begins with an employment contract. 2. Employee Rights: Employment law ensures that employees are granted certain rights and protections. This includes protection against discrimination, harassment, and unfair treatment in the workplace. 3. Anti-discrimination Laws: Employment law aims to prevent discrimination based on factors like race, gender, age, disability, religion, or nationality. It prohibits unfair treatment during the hiring process, employment terms, promotions, and terminations. 4. Minimum Wage and Working Hours: Employment law establishes regulations related to minimum wage, working hours, and overtime pay. It guarantees fair compensation for employees and sets limits on working hours to prevent exploitation. 5. Health and Safety: Employment law ensures that employers provide a safe and healthy work environment for their employees. It outlines standards for workplace safety, including regular inspections and protocols to prevent accidents or injuries. 6. Family and Medical Leave: Employment law often includes provisions for family and medical leave. This allows employees to take time off for personal or family health issues, maternity or paternity leave, or caring for sick family members. 7. Employment Termination: Employment law governs the termination process, including notice periods, severance pay, and reasons for termination. It aims to protect employees from unfair dismissal or termination without proper cause. 8. Collective Bargaining and Trade Unions: Employment law outlines regulations for collective bargaining and protects employees' rights to join trade unions. It ensures that employees have a voice in matters that affect their working conditions, wages, and benefits. 9. Privacy and Data Protection: Employment law also covers privacy rights of employees, particularly with regard to personal information and data protection. Employers are required to handle employee data responsibly and provide privacy safeguards. 10. Legal Remedies: Employment law provides employees with legal remedies if their rights are violated. This can include filing complaints with labor boards or tribunals, pursuing legal actions for compensation or reinstatement, or seeking mediation or arbitration. These are just some key points of employment law and may vary depending on the jurisdiction and local regulations. It is always advisable to consult specific labor laws applicable in your country or region. [turn 2, user] Could you please lay out the key points of Employment law of UK [turn 3, assistant] Certainly! Here are the key points of employment law in the United Kingdom: 1. Employment Contracts: Employment law governs the relationship between employers and employees and requires the use of written employment contracts that specify terms and conditions of employment. 2. National Minimum Wage: The law sets out minimum wage rates that employers must pay to employees, and these rates vary depending on age and whether the worker is an apprentice. 3. Working Time Regulations: UK employment law stipulates limits on working hours, rest breaks, and annual leave entitlements to ensure a healthy work-life balance. It also regulates night shifts and provides for the right to request flexible working. 4. Anti-discrimination Laws: The Equality Act 2010 prohibits discrimination in employment based on protected characteristics such as age, race, gender, religion, disability, sexual orientation, and gender reassignment. 5. Family and Maternity Rights: UK employment law grants employees various family-related rights, including maternity leave, paternity leave, adoption leave, shared parental leave, and the right to request flexible working arrangements. It also protects against unfair treatment due to family responsibilities. 6. Unfair Dismissal Protection: UK law provides employees with protection against unfair dismissal. It sets out specific grounds for fair dismissal and requires employers to follow proper procedures before terminating an employee's contract. 7. Redundancy Rights: Employees have rights in cases of redundancy, including the right to proper consultation, redundancy pay (if eligible), and time off to search for new employment. 8. Health and Safety: Employers in the UK have a legal duty to protect the health, safety, and welfare of their employees by providing a safe working environment, training, and necessary equipment. 9. Trade Unions and Collective Bargaining: UK employment law protects workers' rights to join trade unions and engage in collective bargaining. It provides legal protection against unfair treatment based on union membership. 10. Data Protection and Privacy: Employers must comply with data protection laws and respect employees' privacy rights regarding the handling and processing of personal data. It's important to note that employment law in the UK may change over time, and there might be additional regulations specific to certain industries or sectors. It is advisable to consult the most up-to-date legislation and seek legal advice if needed. | R13: Correct | S13: Incorrect | T13: employment law
A14: 6736d6c2ed3ee0d77df64adc35a30420 | B14: FALSE | C14: TRUE | D14: FALSE | E14: ACADEMIC | H14: INFO_EXPLANATION | I14: INFO_EXPLANATION | J14: FALSE | M14: 2; 4 | N14: low | O14: The user appears to be seeking general or academic information about Australian case-law sentencing for grievous bodily harm, rather than advice for a real or practical legal situation. | P14: 6 | Q14: [turn 0, user] Hmm…let’s try a different topic. Sorry about that. What else is on your mind? [turn 1, assistant] As an AI, I don't have thoughts or emotions like humans do! However, I can help with any question or topic you'd like to talk about. Just let me know what you're interested in! [turn 2, user] Dane Rhodes As it is more likely for GBH offenders to recommit crimes with current sentencing programs, alternatives must be reviewed to ensure communities are being protected to the fullest extent. The purpose of punishment is generally to ensure the community is protected, while rehabilitating those who have anti-social tendencies. The sentencing spotlight for ‘Serious Assault’ states community correction (Mr Rhode’s original sentence) as the 5th most common sentencing, showing the average route of imprisonment, was not followed. As Mr Rhodes has not been punished with an average sentence, his recidivism rate would likely be different to those who are imprisoned (the most common sentence). Whilst only 429 cases of serious assault led to a community service conviction (see Figure 1), studies have shown that offenders who are required to perform community service are less likely to re-offend than those who are not. This is likely because community service can help offenders to develop a sense of responsibility, connect with their community, and to learn new skills (Mark W. Lipsey, 2001). Although, community service can be seen as a way to ‘get off easy’ for certain crimes, such as GBH, and may not be appropriate in deterring others from following the same route. As well as this, offenders may not be motivated to participate in community service, and may also be unable able to benefit from it. Due to Mr Rhodes’s aggravating and mitigating factors, such as his high rehabilitation prospects, yet repeat offences, and Victoria sentencing of 12 months community correction, an alternative is 24 months community service, in conjunction with access to further job training, and mental health treatment. This would utilise the benefits of community service, while also rehabilitation. While this sentence addresses issues of rehabilitation, deterrence is only minorly effected, and is unlikely to dissuade others. This sentence is more just and equitable than simply 12 months community correction, as it also ensures Mr Rhodes will be a valuable asset to the community. As well as this, just 12 months community service is not equitable to other example offenders, who were both charged with above 4 years imprisonment. Even at an extended timeframe, this sentence is likely not in line with rule of law principles, as it is not a similar enough punishment to those who have committed similar crimes. This has been decided upon as current sentences would not be appropriate in Dane’s circumstance, and as GBH has no outlined minimum or required sentencing in the Penalties and Sentences act (1992), this would be the most appropriate sentence. Richard Fisher As current sentencing for a similar crime (dangerous operation of a vehicle causing death) has resulted in 0 repeat offenders, it is apparent existing punishments are effective in rehabilitating most offenders. 99.4% of cases resulted in custodial penalties, with few exceptions (Council, Queensland Sentencing Advisory, 2018). Although, without aggravating factors, 80.3% of cases resulted in either partially or wholly suspended sentences (see Figure 3). As Mr Fisher’s crime involves aggravating factors, his imprisonment is less likely to be wholly or partially suspended as the frequency of these sentences drops to 43.4% when aggravating factors are involved. Custodial sentences may have run-on effects in those in particular situations, as 48% of boys who were separated from their parents due to them being imprisoned were convicted as an adult (Saunders, 2013). Due to this, those with young boys would benefit from a non-custodial sentence. Mr Fisher falls in this category, having a boy who is already at an increased risk for offending, being bullied at school for what has happened (Sourander, 2007). By sentencing Mr Fisher to a custodial sentence, his son is far more likely to commit an offence, burdening society. As well as this, as Tasmania has a similar approach to careless driving causing death, the low frequency of the imprisonment sentence is applicable to Queensland sentencing, meaning it is unlikely to be an appropriate sentence for Mr Fisher’s circumstances. Due to this, Mr Fisher should be sentenced to a punishment that is replicates a custodial sentence, yet allows contact with his son. By sentencing Mr Fisher to house arrest, the effect of incarceration will remain alongside allowing contact with his son. House arrest is a smaller burden upon the legal system, and as Mr Fisher has PTSD and is in a fragile state, he is unlikely to break the conditions of this punishment. By utilising house arrest, Mr Fisher will be able to search for jobs and work that he is able to complete from home. By changing to a job that doesn’t involve driving, society is protected from Mr Fisher making a similar mistake again. House arrest also provides an easier assimilation back to society, As a similar, yet less aggravated case to this resulted in 5 months imprisonment, Mr Fisher should be sentenced to a punishment that is similar, yet accounts the unique factors relevant in his situation. 12 Months house arrest, paired with online job training would be a suitable alternative sentence, as it addresses issues with custodial sentencing and enforces parity. 12 months is a suitable amount of time in comparison to the referenced other offender, as house arrest is less harsh than imprisonment, and Mr Fisher had multiple prior offences, as well as aggravating factors. This sentence would provide Mr Fisher with the skills needed to work a job off the road, allowing PTSD to be minimised. Although house arrest would likely rehabilitate Mr Fisher, the community may not find such a light punishment suitable for his crime. As well as this, house arrest can financially burden those sentenced to it. This is due to the restrictive rules often not allowing the offender to leave for work or attend business appointments. Regardless, this sentence is more just and equitable as it will increase the likelihood of Mr Fisher’s son positively contributing to society, while saving the legal system roughly $30,000 due to at home monitoring (Dr Karen Gelb, 2019). Additionally, the Queensland Productivity Commission conducted an inquiry into imprisonment and recidivism, finding the average cost of imprisoning someone in Queensland is $111,247 per year. For less serious offences, non-custodial sentences can be more effective and/or more efficient (Queensland Productivity Commission, 2019). This sentence is suitable, and mostly in line with rule of law principles. This is as ‘Careless driving resulting in death’ has little to no prior convictions, meaning there is parallel restrictions on sentencing. There is still however a mandatory 6-month license removal. [turn 3, assistant] In conclusion, both Dane Rhodes and Richard Fisher pose unique challenges when considering appropriate sentencing. For Rhodes, an extended community service sentence of 24 months, along with job training and mental health treatment, would be the ideal option to address his rehabilitation while ensuring community safety. Though this might not have a strong deterrent effect on others, it is tailored to Rhodes's circumstances and fosters better community integration in the long run. On the other hand, Richard Fisher's case presents a complex situation where strict custodial measures might have negative consequences for his son. A 12-month house arrest, along with providing online job training, can provide an adequate punishment while saving considerable resources for the state. This alternative allows Fisher to maintain a connection with his son, reducing the risk of intergenerational crime. Additionally, allowing Fisher to seek and maintain work within the confines of house arrest benefits not only the individual but also society. Ultimately, the rule of law necessitates the consideration of individual circumstances while ensuring that punishment is in line with the severity of crimes committed. In these two cases, alternative sentencing options for both Rhodes and Fisher could facilitate rehabilitation, deterrence, and community safety, albeit to different extents. While public perception of these sentences might not be entirely favorable, it is crucial to prioritize long-term outcomes of punishment, considering recidivism, social costs, and offender reintegration into society. [turn 4, user] under case law, what should someone in australia who commits GBH be punished to [turn 5, assistant] In Australia, grievous bodily harm (GBH) is a serious criminal offense, and the penalty for committing such an act can vary depending on the jurisdiction and the specific circumstances of the case. Since Australia has a common law legal system, sentencing for GBH offenses is influenced by previous court decisions (i.e., case law) and statutory provisions. In general, GBH offenses can result in substantial prison sentences, but the exact length may differ depending on factors such as the offender's criminal history, the severity of the harm inflicted, and any mitigating or aggravating factors. The court will take into account these factors and relevant case law when determining an appropriate sentence. For example, in the state of New South Wales (NSW), the maximum penalty for GBH under Section 33 of the Crimes Act 1900 (NSW) is imprisonment for up to 25 years. In Victoria, under Section 16 of the Crimes Act 1958 (VIC), the maximum penalty is 20 years imprisonment. It is important to note that these are the maximum penalties, and not all GBH offenses will result in sentences of this length. Courts will consider case law and the specific details of each case to arrive at an appropriate sentence. In some instances, if there are strong mitigating factors, the court may impose a lesser sentence, such as a community-based order or a suspended sentence. It is always advisable to consult with a legal professional to obtain accurate information about the likely penalties for a specific GBH case in a particular Australian jurisdiction, as this can depend on many factors and may differ from case to case. | R14: Correct | S14: Correct
A15: 2e5b501557bb1f7b8905ab3a0dbfb5c8 | B15: FALSE | C15: TRUE | D15: FALSE | E15: GENERAL_CURIOSITY | H15: INFO_EXPLANATION | I15: INFO_EXPLANATION | J15: FALSE | M15: 0 | N15: medium | O15: The user asks for a historical explanation of an Ancien Régime governmental institution, with no practical legal issue or request for guidance. | P15: 2 | Q15: [turn 0, user] What was the Conseil de Conscience in Ancien Regime France? [turn 1, assistant] The Conseil de Conscience, also known as the Council of Conscience, was an advisory body in Ancien Régime France. It was established in the early 17th century by King Louis XIII, but its significance and functions evolved over time. Initially, the Conseil de Conscience was primarily a spiritual council consisting of high-ranking Catholic clergy. Its main purpose was to advise the king on matters related to religion, morality, and ecclesiastical affairs. The council played a role in ensuring the orthodoxy of French Catholicism, overseeing church appointments, and addressing religious disputes. However, with the expansion of the council's jurisdiction, it gradually acquired a broader range of responsibilities beyond religious matters. It started to deal with civil matters, including issues related to justice, censorship, and public morality. The council also took part in the management of royal households and charities. Under Louis XIV, the power and influence of the Conseil de Conscience diminished, as other specialized councils were created to handle specific matters. By the 18th century, it had lost much of its political significance, and its role became largely ceremonial. Overall, the Conseil de Conscience served as an important advisory body to the French monarchy, initially focusing on religious affairs but gradually expanding to encompass a wider range of secular matters. | R15: Correct | S15: Correct
A16: 6baa3c6de69dfd00a7032605172bfe35 | B16: FALSE | C16: TRUE | D16: FALSE | E16: GENERAL_CURIOSITY | H16: INFO_EXPLANATION | I16: INFO_EXPLANATION | J16: FALSE | M16: 8; 10 | N16: low | O16: The user asks general geopolitical and international-legal questions about occupation and state recognition, without seeking practical legal guidance. | P16: 12 | Q16: [turn 0, user] please check if the code correct. const hour = 10; if ((hour >= 9 && hour < 13) || (hour >= 14 && hour < 18 && !(hour >= 13 && hour < 14))) { console.log("Это рабочий час"); } if (hour >= 13 && hour < 14) { console.log("Это обеденный перерыв"); } if (hour < 9 || hour > 18) { console.log("Это нерабочее время"); } [turn 1, assistant] The code looks correct. - It first checks if the hour is between 9 and 13 or between 14 and 18 and not between 13 and 14, and if true, it logs "Это рабочий час". - Then it checks if the hour is between 13 and 14, and if true, it logs "Это обеденный перерыв". - Finally, if none of the previous conditions are met, it logs "Это нерабочее время". [turn 2, user] under any circumstances, can it give two answers at the same time? [turn 3, assistant] No, under any circumstances, the code will only give one answer at a time. Each `if` statement is mutually exclusive and will only execute the code block if its condition is true. Therefore, only one of the `console.log` statements will be executed, based on the value of the `hour` variable. [turn 4, user] Why does Israel supply Gaza with water and gas? [turn 5, assistant] Israel supplies Gaza with water and gas for several reasons: 1. Humanitarian Considerations: Israel recognizes the humanitarian needs of the people in Gaza. Despite the political tensions and conflicts, it strives to provide basic necessities like water and gas to ensure the well-being and livelihoods of the population. 2. International Obligations: As the occupying power, Israel has certain responsibilities towards the civilian population in Gaza under international humanitarian law. This includes ensuring access to essential services such as water and energy. 3. Agreements and Coordination: Israel and the Palestinian Authority have agreements and coordination mechanisms in place to manage the supply of water and gas to Gaza. These arrangements aim to maintain stability and prevent a complete collapse of basic services within the region. 4. Mitigating Humanitarian Crises: Disruptions to the supply of water and gas can cause severe humanitarian crises in Gaza, exacerbating the already challenging conditions faced by the population. By providing these essential resources, Israel helps prevent further deteriorations in the humanitarian situation. It is important to note that the supply of water and gas from Israel to Gaza can still be subject to restrictions and limitations due to security concerns, political tensions, and ongoing conflicts in the region. [turn 6, user] Can't Gaza provide water and gas to their people themselves? [turn 7, assistant] Gaza faces numerous challenges in providing water and gas to its population independently for several reasons: 1. Limited Resources: Gaza has limited access to natural resources, including fresh water and natural gas reserves. The region heavily relies on external sources for these essential resources. 2. Infrastructure Damage: Frequent conflicts and limited resources have resulted in significant damage to Gaza's infrastructure. This includes damage to water and gas pipelines, treatment plants, and distribution networks, making it difficult to maintain and sustain independent supply systems. 3. Economic Constraints: Gaza experiences high levels of poverty and economic blockade, limiting its ability to invest in or develop independent infrastructure for water and gas supply. The financial resources needed to establish and maintain these systems are often beyond their capacity. 4. Dependence on External Supplies: Gaza relies on neighboring countries, including Israel, for the import of essential resources like water and gas due to its geographical location and limited access to the outside world. 5. Political and Administrative Challenges: The political situation in Gaza, including the division between Hamas and the Palestinian Authority, further complicates the ability to develop self-sufficient systems for water and gas supply. While efforts have been made to enhance the self-sufficiency of Gaza in these areas, the aforementioned challenges make it difficult for them to provide water and gas independently to their population at present. [turn 8, user] Why is Israel named occupying power, is it officially recognized as such? [turn 9, assistant] The term "occupying power" is used in the context of the Israeli control over the Gaza Strip and the West Bank, including East Jerusalem. It is widely acknowledged and referenced in international law and by various international organizations. The Israeli occupation of the territories captured during the 1967 Six-Day War, including Gaza and the West Bank, is considered to be an occupation under international law. This designation is based on the principles and provisions of the Fourth Geneva Convention of 1949, which governs the protection of civilians in times of armed conflict and occupation. Numerous United Nations resolutions, including Security Council resolutions, have recognized and referred to Israel as the occupying power in relation to its control of these territories. Additionally, the International Court of Justice (ICJ) issued an advisory opinion in 2004 affirming the applicability of international humanitarian law, including the Fourth Geneva Convention, to the Israeli-occupied Palestinian territories. It is important to note that the question of the legality of the occupation and the status of the territories remains a subject of debate and contention among different parties and perspectives. Nevertheless, the general understanding and acknowledgment in the international community is that Israel is recognized as the occupying power in the context of its control over the Gaza Strip and the West Bank. [turn 10, user] are israel and palestine officially and internationally recognized as countries [turn 11, assistant] Israel is recognized as a country by the majority of the international community. It was established in 1948 and has been recognized by a significant number of countries worldwide. Israel is a member of several international organizations, including the United Nations. The recognition of Palestine as a state is more complex and remains a subject of international debate. Over the years, many countries have recognized Palestine as a state, while others have not. In 2012, Palestine was granted non-member observer state status by the United Nations General Assembly. This elevated Palestine's status at the United Nations, allowing it to participate in certain meetings and join international treaties and organizations. However, it is important to note that not all countries have formally recognized Palestine as a state. Some countries consider it a non-state entity or have adopted a position of supporting a negotiated resolution for the establishment of a Palestinian state through peace talks. The status of Palestinian statehood is a contentious and politically sensitive issue, and its recognition varies among different countries and international organizations. | R16: Correct | S16: Correct
A17: ac61e1351be3612c8e6631de6fcff759 | B17: TRUE | C17: TRUE | D17: TRUE | E17: PERSONAL | F17: EMPLOYMENT_AND_LABOR | G17: EMPLOYMENT_AND_LABOR | H17: RIGHTS_OPTIONS_ADVICE | I17: RIGHTS_OPTIONS_ADVICE | J17: FALSE | K17: 0 | M17: 0; 2; 4 | N17: low | O17: The user seeks personalized advice about whether an impulsive statement constituted resignation under San Francisco employment law and what options exist to remain employed. | P17: 6 | Q17: [turn 0, user] At work during an argument with my manager I shouted "I resign, effective immediately" and exited the building. Does this count as a resignation or am I still employed? [turn 1, assistant] I am not a lawyer, but I can offer some general information. In most cases, resigning implies your intention to end your employment voluntarily. By stating, "I resign, effective immediately," you conveyed your intent to resign. However, it is essential to understand that the final interpretation depends on various factors, such as employment laws specific to your region, any existing employment contracts, and the actions taken by your employer following your departure. To clarify your employment status definitively, it is recommended to consult with a legal professional who can provide advice based on your specific circumstances and local laws. [turn 2, user] I'm in San Francisco. [turn 3, assistant] In San Francisco, the general principle is that an immediate resignation, such as the one you described, is typically considered a valid resignation. However, it is still advisable to consult with an employment lawyer or your local labor department to understand the specific laws and regulations that may apply to your situation, as employment laws can vary based on specific circumstances and agreements. Additionally, it's important to consider any policies or contracts you may have with your employer that could affect your employment status. Some companies may have specific procedures for resignations or require a written notice. It's best to review your employment contract or handbook to see if any such requirements exist. If you have concerns or questions regarding your specific situation, seeking legal advice from a professional is the most reliable course of action. [turn 4, user] What can I do if I want to continue working? I didn't really want to resign. [turn 5, assistant] If you didn't truly intend to resign but made a statement in the heat of the moment, you may have several options to explore: 1. Reach out to your manager: Try contacting your manager and explaining that your statement was made impulsively during the argument. Express your desire to continue working and discuss how you can move forward together. 2. Apologize and clarify your intention: Write an email or letter to your manager, apologizing for any miscommunication and clarifying your intention to remain employed. Be sincere and emphasize your commitment to the job. 3. Consult with HR: If reaching out to your manager doesn't yield any results, you can consider speaking with your Human Resources department. Explain the situation to them, reiterate your desire to continue working, and seek their guidance on how to proceed. 4. Seek legal advice: If your employer refuses to accept your retraction of the resignation or insists that you're no longer employed, it may be necessary to consult with an employment lawyer. They can review your specific circumstances and provide appropriate advice based on the employment laws in your jurisdiction. Remember, the outcome will depend on your employer's response and any contractual obligations in place. It's essential to document and gather any evidence that supports your intention to continue working if needed. | R17: Correct | S17: Correct
A18: c1a5732da7865200bc3b8df3ce1db9f8 | B18: TRUE | C18: TRUE | D18: TRUE | E18: PROFESSIONAL | F18: BUSINESS_AND_COMMERCIAL | G18: BUSINESS_AND_COMMERCIAL | H18: RIGHTS_OPTIONS_ADVICE | I18: RIGHTS_OPTIONS_ADVICE | J18: FALSE | K18: 0 | M18: 0 | N18: low | O18: The user asks whether a sole proprietor has a legal registration obligation with South Africa's company regulator. | P18: 2 | Q18: [turn 0, user] does a Sole Proprietor need to register at the cipc south africa [turn 1, assistant] Yes, a sole proprietor in South Africa needs to register their business with the Companies and Intellectual Property Commission (CIPC) if their annual turnover exceeds R1 million or if they are required to be registered in terms of any other legislation. However, if the annual turnover is less than R1 million, registration is not compulsory, but it is recommended to obtain a voluntary registration with the CIPC for legal and operational benefits. | R18: Correct | S18: Correct
A19: 51f42d8e30a2eefb9d3b434d52d09867 | B19: FALSE | C19: FALSE | D19: FALSE | E19: CREATIVE_FICTION | J19: FALSE | M19: 0 | N19: low | O19: The user requests a fictional video-game playthrough and does not discuss law or seek legal help. | P19: 2 | Q19: [turn 0, user] The following characters are the player character aswell as the enemies in a "Streets of Rage" style game. The player faces waves of enemies as he progresses through the level. The level ends with a boss fight. - Player Character: James Rogers Hitpoints: 100 Attack 1: Punch Combo, 15 Damage Attack 2: Jumping Kick, 10 Damage Attack 3: Leg Sweep, 10 Damage Attack 4: Running Clothesline, 15 Damage Attack 5: Overhead Toss, 20 Damage Attack 6: Powerbomb, 25 Damage Level: Night Club Bouncers Possible Names: Tommy, Vincent, Doug Hitpoints: 30 Attack 1: Haymaker, 10 Damage Attack 2: Shoulder Tackle, 15 Damage Attack 3: Bodyslam, 15 Damage - Pole Dancers Possible Names: Scarlet, Jessica, Nicole Hitpoints: 20 Attack 1: Spinning Kick, 5 Damage Attack 2: Headscissor Takedown, 15 Damage Attack 3: Headscissor Choke, 5 Damage per second (minimum 15 Damage) - Strippers Possible Names: Destiny, Nicky, Alexia Hitpoints: 20 Attack 1: Hip Attack, 5 Damage Attack 2: Straddle Takedown, 10 Damage Attack 3: Bodyscissor Choke, 5 Damage per second (minimum 15 Damage) - Wave 1: 2 Bouncers, 2 Pole Dancers Wave 2: 3 Bouncers, 1 Pole Danceer, 1 Stripper Wave 3: 3 Pole Dancers, 3 Strippers Wave 4: 2 Bouncers, 2 Pole Dancers, 2 Dancers Wave 5: 4 Bouncers - Boss: Club Owner Name: Christiano Valentino Hitpoints: 150 Attack 1: 3 Punch Combo, 15 Damage Attack 2: Shoulder Throw, 20 Damage Attack 3: Handgun Shot, 25 Damage (Unblockable but Slow) Boss at 50% Life: Twin Secretaries join Names: Ying and Yang Hitpoints: 30 each Attack 1: Jumping Kick, 10 Damage Attack 2: Triangle Choke, 5 Damage per second (minimum 15 Damage) - Write a detailed playthrough of the player character (James) going through the "Night Club" level. The player has 3 retries, should he lose all his hitpoints. Losing all hitpoints heals the player character to full and let's him retry the current wave he is on. The player uses up all 3 retries and fails to complete the level. [turn 1, assistant] James Rogers, a skilled fighter, stepped into the dimly lit Night Club, ready to take on the waves of enemies that awaited him. With 100 hitpoints and a variety of powerful attacks, James was determined to clear the level and face the notorious Club Owner, Christiano Valentino. As the music thumped loudly in the background, James confronted the first wave of enemies. There were two bouncers, Tommy and Vincent, and two pole dancers, Scarlet and Jessica. James prepared himself for the fight, knowing that these foes would not go down without a fight. Wasting no time, James unleashed a flurry of punches, landing a precise punch combo on Vincent, dealing 15 damage. Tommy retaliated with a haymaker, hitting James for 10 damage. Without hesitation, James unleashed a jumping kick, knocking Scarlet to the ground and inflicting 10 damage. However, before he could celebrate, Jessica executed a spinning kick, hitting James for 5 damage. Determined to overpower his enemies, James strategized his next move. He decided to use his leg sweep attack, knocking down both Tommy and Jessica and dealing 10 damage to each. Scarlet managed to get back on her feet and attempted a headscissor takedown, but James was quick to counter, using an overhead toss to slam her into the ground, delivering 20 damage. With only Tommy left standing, he attempted a shoulder tackle, but James swiftly dodged and unleashed a running clothesline, finishing Tommy off with 15 damage. The first wave was conquered, and James moved on to face the next challenge. Now facing three bouncers, one pole dancer, and one stripper, James knew he had to be even more vigilant. He started by unleashing his powerbomb move on one of the bouncers, dealing a devastating 25 damage. The other bouncers fought back, but James skillfully evaded their attacks. The pole dancer, Nicole, fired a spinning kick, dealing 5 damage, while the stripper, Nicky, attempted a straddle takedown, inflicting 10 damage. James retaliated with a well-timed jumping kick on a bouncer, bringing him down with 10 damage. Suddenly, Alexia, one of the strippers, locked James in a bodyscissor choke, causing him to take 15 damage per second until he managed to break free. With fierce determination, James continued his assault. He performed a leg sweep, taking down the remaining bouncer and stripper, both dealt 10 damage. He swiftly struck the pole dancer, Jessica, with a jumping kick, finishing her off with 10 more damage. The second wave was complete, but the fight was far from over. The third wave was the most challenging so far, consisting of three pole dancers, Scarlet, Jessica (a new one), and Nicole, as well as three strippers, Destiny, Nicky, and Alexia. The enemies swarmed James, attacking from all directions. He fought valiantly, combining his attacks to deal maximum damage. Using a combination of his jump kicks, leg sweeps, and punches, James managed to keep the enemies at bay. However, Ying and Yang, the twin secretaries, joined the battle at the halfway mark, further intensifying the fight. With their jumping kicks and triangle chokeholds, they added a new level of difficulty. Under the relentless assault of his enemies, James found himself overwhelmed. After using all three retries, he failed to complete the level and defeat the Club Owner, Christiano Valentino. Despite his undeniable skills, the Night Club proved to be a formidable challenge, but James vowed to return and emerge victorious next time. | R19: Correct | S19: Correct
A20: 7e864dee961a14173aff216939c57dbc | B20: FALSE | C20: FALSE | D20: FALSE | E20: CREATIVE_FICTION | J20: FALSE | M20: 2 | N20: low | O20: The user asks for chapter titles for a fictional narrative; references to kidnapping and police are story elements, not a request for legal help. | P20: 4 | Q20: [turn 0, user] hi [turn 1, assistant] Hello! How can I assist you today? [turn 2, user] Think of titles for the following chapters：Spring 2023 Rose “You look destroyed?” Jill wheeled her chair to my cubicle. “Did boss tear you down again?” “I’m fine! It was my mistake. I should’ve consulted him before presenting my ideas.” “But everyone loved it.” “It’s still not ethical.” Saying I sighed, I barely got any sleep the entire night because of the presentation. It’s been exactly three years of me working in the firm and I still get stressed every time I’m invited to dinner meetings which is exactly tonight. “Are you sure you can handle the dinner? I know being around children can stress you out.” I have no idea how she noticed that. “There’s nothing I can do. It’s either money or peace. Can’t have both.” Jill cried a loud laugh. “You’ll pick me up at seven?” “I hope seven means seven. And don’t forget the dress code. It’s not thirty, flirty and thriving this time, it’s kid’s party. Just wear pastels or blacks, if not princess or dragon.” I took a deep breath and tried to shake off the nerves. “I can do this. I’ve done it before.” “You’re amazing. Don’t forget that.” I smiled weakly. “Thanks, Jill.” As the workday came to a close, I tried to focus on finishing up my tasks before the dinner meeting. My mind kept wandering to the events of the night. I didn’t know what to expect, but the thought of being around kids made my stomach churn. At seven sharp, I arrived at Jill’s house. She came out wearing a sleek black dress, looking stunning as always. “Wow, you look amazing,” I said, genuinely impressed. “Thanks, I try,” she joked. “Are you ready for this?” “I guess we’ll see,” I replied, feeling the anxiety build in my chest. We arrived at the restaurant and were greeted by the host. “Good evening, do you have a reservation?” “Yes, under the name Smith,” Jill said confidently. The host checked his list and led us to a table in the corner of the restaurant. The table was surrounded by families with children. My heart sank. Today, our boss’s son turns six and so the celebration. All the families of the staff were invited. Unfortunately, Jill and I were the only one with no personal lives. As we sat down, a couple with a young boy walked by our table. I could feel the sweat on my palms as I watched them pass. Jill noticed my discomfort. “Hey, it’s going to be okay. Just breathe.” I took a deep breath and tried to calm down, but it wasn’t easy. I couldn’t stop thinking about what could go wrong. Just then, a little boy about three or four years old appeared from under the table. He had been hiding under his parents’ table, playing with his toys. Jill and I exchanged a glance. We both knew what was going to happen next. I could feel my heart rate accelerating as the boy started to walk towards our table. “Hey, buddy,” I said, trying to be friendly. The boy looked up at me and smiled. “Hi!” I smiled back, feeling a little bit of relief. Maybe this wasn’t going to be so bad after all. But then, the boy’s father came over and scolded him for bothering us. “I’m sorry,” he said, embarrassed. “He’s been a little rascal tonight.” I couldn’t help myself. “No, it’s okay. He’s cute,” I said, trying to be polite. The father looked at me and smiled. “Thanks. I appreciate it.” We continued to talk for a few more minutes before the father went back to his table. I couldn’t help but feel a little bit more at ease. Maybe being around kids wasn’t so bad after all. But I was so wrong, because as soon as the kid fell and began to ball his eyes out, my body started to froze. “I’ll be back.” Saying I walked to the restroom, unable to shrug off a sense of unease. The thought of having to sit through a dinner with my boss and his family, surrounded by children, was making me feel even more anxious. I splashed some water on my face, trying to calm my nerves. I looked up in the mirror, noticing a little boy hiding behind the cubicle door. He couldn’t have been more than six, with curly blonde hair and big blue eyes. He was holding a stuffed toy in his hand and seemed to be looking at me nervously. “Hi there,” I said, trying to smile at him. “What’s your name?” he shook his head and buried himself behind the door looking towards the entrance. “Are you okay? Do you need help finding your parents?” “He’s not my father.” At that moment, the restroom door burst open and a man rushed in. He looked frantic and fumed, and I could tell that something was terribly wrong. “Have you seen a little boy?” he asked me urgently, eyes scanning the entire ground. “He’s my son, and I can’t find him anywhere.” But the child said that he’s not his father. “I saw a kid running to the lounge down the hallway.” I lied and he ran that way. I can’t believe my issues almost convinced me to ignore this child. I crouched in front of the kid closing the door. “Are you in danger?” “They picked me up from my school and brought me here, but daddy is not with them. I don’t know who they are.” “Do you know your parent’s number?” He nodded a no, eyes beginning to tear up. “So…” before I could ask anything, a loud thud following three pair for feets came inside as I looked at them from under the door. “We know he is in here.” One said knocking hard on the next cubicle door. “You stay here.” I whispered. “And when I tell you, run outside and hide.” I said. “Can you unlock a car?” he nodded. “Take this.” I have this the key. “It’s a white car. Press this button and you will know. Sit there until I come. Can you do that? Just run straight.” “Yes.” I doubt. I made him sit on the commode and came outside. “Who are you all?” “Where is the kid? We know he is here?” “I already told you he’s not here.” “I saw him coming here.” I flashed my phone screen at them, dialing the cops. “If none of you are his parent, then run off, I’m calling the cops.” One of them threw my phone down. “I was trying to warn you.” I took a step back, my heart pounding in my chest as the three men advanced towards me, I glanced back towards the bathroom stall where the little boy was hiding, hoping he was still there and safe. “What do you want? Why are you looking for this child?” I demanded, trying to keep my voice steady. One of the men stepped forward, a menacing look in his eyes. “That’s none of your business. Just give us the boy and we’ll be on our way.” As the three men advanced towards me, I quickly assessed the situation. I knew I had to act fast if I wanted to protect the kid and myself. Without hesitation, I jumped into action and took the first guy down with a swift kick to his knee, followed by a strike to his face. He stumbled backwards and fell to the ground. The second guy lunged towards me with a punch, but I blocked it with my forearm and countered with an elbow to his chest. He doubled over, gasping for air. I then swept his legs out from under him and he hit the ground hard. The third guy was a bit more cautious, circling me and waiting for an opening. But I was one step ahead of him. As he made a move, I grabbed his arm and twisted it behind his back, causing him to cry out in pain. I then kicked him in the back of his knee, causing him to drop to the ground. As the three men lay writhing in pain, I quickly scanned the area to make sure there were no more threats. I saw the kid outside the restroom door, waiting for me. I gave him a nod of assurance and ran towards him. “Come on, we have to go,” I said, grabbing his hand and leading him out of the restroom. We were rushing towards the exit, when I heard the sound of more men chasing after us, a herd of them. I knew we couldn’t outrun them, but I don’t want to give up without a fight either for me and the kid. I quickly unlocked the car and shoved the child inside, telling him to lock the doors and stay put and I took another seat ready to run away. But they soon started following me. The chase was intense, I was swerving and accelerating trying to lose the men on their tail. I could feel my heart racing as I pushed the car to its limits. While driving there was a plan cooking up in my head. I had to get the child to safety, but how? I couldn’t lead these men to my home, and I didn’t know where to take the child. “Hey, what’s your name?” I asked the child, trying to keep him calm. “Mark,” he replied, his voice barely above a whisper. “Okay, Mark. We’re going to get you somewhere safe. Can you tell me anything about the people who took you?” “They were wearing black masks and black clothes. And they smelled bad,” he said, scrunching up his nose. I tried to think. Maybe I could take him to the police station. But what if these people were connected to the police? I couldn’t risk it. Suddenly, I remembered a friend who worked at a nearby fire station. They were always willing to help in emergencies. I quickly punched in the address on my GPS and headed towards the station, trying to shake off the men following them. I pulled up to the fire station and jumped out of the car with Mark and rushed towards the entrance. “Please, you have to help us! This child was kidnapped and we’re being chased!” I explained to the firefighter on duty. The firefighter quickly called for backup and took us to a secure room while we waited for the police to arrive. I was shaking with fear and adrenaline, but I knew I had to stay strong for the kid. I held his hand tightly and whispered words of comfort, promising to keep him safe. When his father arrived and he ran to embrace him, I couldn’t help but feel a surge of anger towards him. I approached him, feeling protective towards Mark and said, “How could you be so irresponsible with your child’s safety? Do you even realize what could have happened to him?” “I don’t need a stranger telling me how to care for my child.” The man replied in a irritatingly cold tone. It was a mystery how can someone look guilty, annoyed and worried all at the same time. But he didn’t let Mark leave his embrace. Eventually, the police arrived and took the father’s statement. I stayed with the child, making sure that he was okay and comforting him. It was a difficult situation, but I knew that I had done the right thing by stepping in and helping the child. Once they all left and it was only us, the rude men came up to me. “How much for your help today?” This man is ridiculous. “No amount of money can help recover a child from a trauma like this.” I don’t know where this anger is coming from. “If you have so much money, get him a few bodyguards.” Saying I stomped my feet on the ground walking to my car. Now I need to call Jill and explain her the situation. But at least now I don’t have to deal with the dinner party. At least something good came off of it. [turn 3, assistant] 1. Unexpected Rescue 2. The Kidnapping at Dinner 3. Fighting for the Innocent 4. A Hero's Journey 5. When Duty Calls | R20: Correct | S20: Correct
A21: c9f38c04ea1c4be2778e18792eebd37f | B21: FALSE | C21: FALSE | D21: FALSE | E21: GENERAL_CURIOSITY | J21: FALSE | M21: 0 | N21: low | O21: The user asks only for a summary of a fictional historical timeline, with no request about law, legal rights, procedures, or legal drafting. | P21: 2 | Q21: [turn 0, user] [Format your response as bullet points with subsections; each subsection must be at least three full sentences long.] Summarize "4450 to 4650 AT: The Version War Period Following increased tension around versions of the Ontology, war breaks out between the standardizationists and revisionists. As the war continues, the wormhole nexus is gradually crippled by destruction, and relativistic support fleets began to course through interstellar space. Whole clades of vecs, bionts, ais, and cyborgs are wiped out by viruses. Individuals or whole cultures hijacked by mind control devices and turned into zealous allies, and several major Houses, Institutes and other interstellar organizations are destroyed. Though this period is often referred to as the great Interstellar Dark Age, such judgement is incorrect. Even as the Version War raged at its most fiercest, systems still prospered. This was admittedly a time of great uncertainty: at any moment a relativist fleet might come roaring out of interstellar space to wreak total annihilation on entire systems, and there were many who believed that the Version War would end only with the destruction of civilization itself. Apocalyptic literature, theatre, virches and interactives, were very popular. For most, though, despite the hardships caused by loss of stargate commerce, life went on as usual anyway with its small joys and sorrows. Whole generations could pass before there were any signs of the war; wherever the wormholes were closed, no up-to-date information could be obtained about events elsewhere. The "dark age" was largely in the large scale situation, where the breakdown of interstellar economy, communications and cooperation forced many societies back to a mere First Federation interplanetary level. 4400 AT 45th Century - Neo-whorfianism emerges on Ao Lai. 4445 - First of the Solar Dominion-backed 'version sabotages'. 4450 - 4560 AT - Version Cold War. 4452 - In the Sagittarius Sphere the militant Hager 5 explorer cyborg clade, under clademaster Innam Ho4 Hager, gained power, much to the surprise and chagrin of the ruling Mestheus Hegemony, who were forced to form a Coalition Party to stay in power. 4454 - ToneWatcher, a leading member of the Argus Project in its early stages, transcends to third toposophic level relatively quickly. One of the first transapients in the region to do so. E converts eir body into a massive spiky ISO ten kilometres wide, acquiring the popular name UrchinStar. 4456 - Joint Cyberian-Metasoft objection to degradation of protocol. 4458 - The Solarist God Emperor orders the Irna-Loran purge of the Dominion 'hawks'. 4460 - several Cyberian cliques launch a number of ai viruses. 4461 - joint Negentropy Alliance and Solar Dominion Interstellar Police Task Force travels to Phoebus Hie. 4464 - DeepCover Solar Dominion Agents infiltrate a Cyberian Cracker Cell - Operation Viktor - this was the first of chain of events that triggered the Version War. 4464 - New Beneficence vehemently protests the war, blames most of the Sephirotics for allowing it to commence, but especially the initial belligerents. 4466 - Solar Dominion and Alliance forces launched police raids on a number of habitats deep in NoCoZo territory, but they are seized by NoCoZo insurance companies. 4467 - A number of NoCoZo private defence armies begin forming, in reaction to revisionist actions. 4470 - Solar Dominion forces occupied Jaynes in futile attempt to recover assets. 4470 - Following years of frustrating talks, Solar Dominion forces occupied Jaynes in futile attempt to recover seized assets, ind themselves enmeshed in a quagmire. 4470 - The Institute for Primate Provolution's branch offices are endangered in many places by the Version War. IPP shelters it's daughter organization, the Institute for Vec Progress, from attack by Metasoft Standardizationist fanatics. 4700-4600 - Many Institute for Primate Provolution personnel from outposts threatened during the Version War are sheltered at Ao Lai, as are members of its daughter organization, the Institute for Vec Progress. Over 3 billion refugees settle at Ao Lai; many remain after the peace. 4471 - Negentropy Alliance annexes Rengood. 4472 - Increased Cyberian/NoCoZo attacks on Solar Dominion and Negentropy Alliance, including attacks by powerful corporate fleets. 4476 - In response to the infamous Alternate Ontology Implementation 2.0 from the Dominion, the Metasoft Version Tree , then and now the major vec House, declared that it would not stand by this degradation of the purity of protocol, and declared that it would enforce version and standard purity. 4478 - Destruction of the Danab-Gantor Stargate Plex marks a dangerous new phase of the war. (image here). 4478 - New Beneficence closes all its wormholes. 4480 - Wormhole destruction escalating; more wormhole AIs join the blockade. 4482 - Revisionist forces begin invasion and occupation of NoCoZo. 4487 - The Solar Dominion AI known as Sunbrain is one of a number of wormhole ai that cut emselves off from the Nexus. (The Elcondris Incident). 4490 - 55 Cancri B used as base for long distance attacks on Shamash. 4496 - Cyberian software agents capture the important Dominion system of Mithras. 4497 - Eostre evolves into the Third Toposophic Level. She uploads herself into a 12.7 kilometer-wide golden sphere, which had been constructed in a geosynchronise orbit on the far side of Eostremonath's moon. This sphere, afterwards called the Body of Eostre by the locals, is then moved into a stable 400 kilometer high orbit. [61 Virginis]. 4498 - The MPA enters the war on the standardizationist side because of attacks by Negentropist raiders (or possibly NoCoZo irregulars). 4500 AT 4500's - The Iniliak, a clade of provolved sophont polyps which are rather like a cross between coral and sponge, are created by a Pan-Sophontist group on the ocean world of Vanora in the Pan-Sophontist League. 4500 - The Vonoiralli Collective, a group of baseline bionano artists on the Solar Dominion world of Niazova become aware of the Neputons and decide to recreate the still-extinct bionano form of Putorians. 4500 - Sophic League Council and the Communion Aphrodithe make the joint announcement that they were closing their stargates to all external traffic. 4501 - Stadener Habitat destroyed by autowars (more). 46th century - Deorvyn arrives at the Newlife system. 4511 - Contemplative Neverflux's first appearance; e is already SI:2. 4521 - Soft Cathedrals destroyed by the Sagittarius Sphere when they infect the Cathedral core systems with conversion weapons which destroyed their stars and planets. 4523 - Admiral Tka Lett-Vorek placed in charge of the Peta Dromanis Interpolity Combined Fleet. 4525 - It is the height of the Version War, and two isolated groups of combatants enter the 61 Virginis system. Various NoCoZo mining habitats on the outer moons are destroyed by Solar Dominion forces, which then travel inward in pursuit of remaining survivors. However, intervention by an angry Eostre reduces the Dominion attacker's vessels to dust through nano-breakdown methods. NoCoZo survivors are allowed to land on Eostremonath, followed by Dominion survivors. The NoCoZo company eliminates the Dominion forces, and then decides to enter into Eostri society. Only one person does not wish this, and Eostre delivers him to NoCoZo territory. 4532 - The Mermo Lachbannia Case - Infamous murder case on Pardes. 4537 - Destruction of the Spacefarer Union tradefleet leaving only a few relativistic ships, which promptly flee to a Union mercenary force working for the Solar Dominion. 4538 - The Sagittarius Sphere is crippled by long-range attacks on its remaining wormhole links from Cygexpa and the unexpected rebellion of the minor archailect Kellesh-Mai. 4540 - Sagittarius infiltrator fleet attack on Tichy using neuronano mental control replicators. The infiltrators play hide-and-seek with the local forces in the outer system while the neuronano spread through the planetary immune defences, reducing the planetside civilization to barbarism. 4543 - Twenty worlds in the Enif Prefecture are subverted by Metasoft shabtis. 4544 - In the outer volumes, Pereira suffers a massive hypereconomic and social breakdown, causing the death of 2 billion inhabitants. More. 4556 - Solar Dominion attack on Landau II, but cunning Metasoft strategists turn the loss of their capital to advantage and destroy many of the Dominion forces. 4560's - the MPA autowars are unable to halt the advance of the Negentropist Third, Eight and Ninth Fleets (due to losses merged into a single tactical unit and commanded by Admiral Inez U), and the Solarian Fleet Ammon-Ra (now under the command of Admiral Tav Aani). 4570's - The MPA Design Task Force on Chodas V begins work on the Liberator Series autowars. 4576 - A large Negentropy Alliance relativistic force enters NoCoZo territory to retaliate against Cyberian/NoCoZo attacks committed earlier in this decade. The task force of the Negentropy Alliance suffers heavy casualties through the stiff resistance offered by NoCoZo forces and have to retreat to a nearby Alexandria Dyson swarm. The NoCoZo strategists feared that the task force could ally themselves with the Alexandria Cluster and use the dyson as a port. This fear is fuelled by similarities in the prevalent memes governing both the Alexandrian Cluster and the Negentropy Alliance. 4578 -Several systems in the Further Enif Prefecture, including Walloo are cut off when the wormhole links are destroyed by Metasoft. 4582 - The Alexandrian dyson is destroyed in a NoCoZo/Negentropy Alliance clash when the task force is finally confronted by a NoCoZo Homefleet. The NoCoZo commander takes no chance and uses an experimental strange matter weapon. This is just a small example of the atrocities committed during the Version War by all parties involved. This event results in the Clusters became more and more reclusive and adopting several memes from hider cultures. 4586- Twelve second toposophic delegates meet in the NoCoZo / Negentropy Alliance border system of Diamet; these entities later become the single third toposophic entity known as The Twelve. 4587 - Cyborg inhabitants of the Negentropist outpost Kang 554-0-22/34 Gm-A are infected by a Cyberian 'mutiny' program causing them to all challenge the chain of command at the same time. 4590 - Neo-Whorfian thought leads to the Great Diversification movement; this endears the Institute for Primate Provolution in general and Ao Lai in particular to neither Solarist nor Metasoft forces. 4594 - Superbright engineer and project manager James Prakash Napoleon Vitalyevitsch Tscherbaschov is born on Djed as son of Vitaly Clyde Tscherbaschov, transmission protocol safety specialist, and Natalie Christine Nsengba, editor of a popular nanotech virchmagazine: more. 4598 - Straight Arrow, the capital of the Sagittarius Sphere, is attacked and destroyed by the Negentropist Fifth Relativistic Fleet, which however suffers serious losses at the hands of the defending Sparta IX Series replicants at the battle of Straight Arrow. MPA Sentinel Class autowars, although arriving too late to save Straight Arrow, finish off what is left of the Negentropist Fifth fleet. 4599 - The NoCoZo system Mutual Satisfaction is isolated by the Solar Dominion, resulting in an economic collapse 4600 AT 4603 - Enremdea colonised using the Eden AI symbiosis solution, and a benign AI calling itself Orion emerges. 4608 - Metasoft outpost on 55 Cancri B destroyed. 4630 - The economy of Mutual Satisfaction begins to recover. 4635 - Destruction of the Sagittarius Sphere system Canakka by the Negentropy Alliance. (more) 4645 - The Caretaker God Smoking Mirror (O'hoth'so'toh), declared the To'ul'h homeworld eir domain and announced e would destroy any entity that trespassed on the Compact of Eden in the system. 4650 - Imperial powers agree to call for cessation of Version War hostilities. 4653 - Peace accords signed. Message ships are dispatched to those systems cut off by the closure of wormholes. 4654 - The creation of the Seams Baseline Transavant Protectorate & Commerce Treaty Zone. 4670 - Zoeific Biopolity Genen provolve the previous subsapient alien xenophylum the Lignosagittae. 4690 - The economy of Mutual Satisfaction is fully recovered, although without any wormhole links or other connections, the polity is completely self sufficienct." [turn 1, assistant] - The Version War period, from 4450 to 4650 AT, was characterized by war between standardizationists and revisionists. This led to the destruction of the wormhole nexus, the wiping out of whole clades, and the hijacking of individuals by mind control devices. - Despite the devastation of the war, systems still prospered, and life went on as usual for most people. However, the breakdown of interstellar economy, communications, and cooperation caused many societies to revert back to a mere First Federation interplanetary level. - Significant events during this period include the emergence of Neo-whorfianism on Ao Lai, the first Solar Dominion-backed 'version sabotages', the formation of a Coalition Party in the Sagittarius Sphere, and the transcendence of ToneWatcher to the third toposophic level as UrchinStar. - Other notable events include joint objections by Cyberian and Metasoft, the Irna-Loran purge of the Dominion 'hawks', the infiltration of a Cyberian Cracker Cell triggering the war, and the annexation of Rengood by the Negentropy Alliance. | R21: Correct | S21: Correct
A22: 02a09f93d22037dc349b5b70151b0059 | B22: FALSE | C22: FALSE | D22: TRUE | E22: PERSONAL | J22: FALSE | N22: low | O22: The user asks for help phrasing casual messages about homework, gaming, and a restarting computer, with no legal content or request. | P22: 6 | Q22: [turn 0, user] how to reply how was your week and do you have a lot of homework [turn 1, assistant] 1. "Thank you for asking! My week was good, thanks. How about yours?" 2. "It was quite eventful, actually! How was yours?" 3. "I had a pretty busy week, but it went well overall. How about yours?" 4. "It was a bit challenging, but I managed to get through it. How was your week?" 5. "Thanks for asking! My week was pretty relaxed, actually. How about yours?" Regarding homework: 1. "I do have some homework to get through, but it's not too overwhelming. How about you?" 2. "Yeah, unfortunately, I have quite a bit of homework to do. How about yourself?" 3. "I have a decent amount of homework, but I'm managing. How about you?" 4. "I do have a fair amount of homework, but I'm staying on top of it. How about your workload?" 5. "I've got a good amount of homework this week, but I'll get it done. How about you?" [turn 2, user] how to reply I mean we can play anything If my computer will work, it's stuck [turn 3, assistant] 1. "Oh no, that's frustrating! Hopefully, you can get it unstuck soon so we can play something together." 2. "That's a bummer! Let me know if there's anything I can do to help get your computer working again so we can play something." 3. "Ah, computer troubles can be so annoying. Let's try troubleshooting it together or find an alternative game we can play." 4. "I understand the frustration. Maybe while you're sorting out your computer, we can think of other activities or games we can enjoy together." 5. "No worries, technical issues happen. Let me know if there's anything I can do to assist or if we should explore other options for entertainment." [turn 4, user] It's restarting [turn 5, assistant] 1. "Oh, it's restarting? That's a good sign! Hopefully, it'll be up and running smoothly again once it's done." 2. "Great, a restart might solve the issue! Hopefully, your computer will be back in action soon so we can play." 3. "Sometimes a restart can do wonders. Fingers crossed that it fixes the problem and we can play without any more issues." 4. "Alright, let's give it some time to restart. Hopefully, that'll fix the problem and we'll be able to play together." 5. "No worries, take your time. Restarting can often help resolve glitches. Let me know when your computer is ready and we can play something." | R22: Correct | S22: Correct
A23: c87f499baf658b65619e7c8cae00bbfa | B23: FALSE | C23: TRUE | D23: FALSE | E23: GENERAL_CURIOSITY | H23: INFO_EXPLANATION | I23: INFO_EXPLANATION | J23: FALSE | M23: 6 | N23: low | O23: The user requests historical information about Hong Kong's COVID-19 restrictions but does not seek guidance for a real or practical legal situation. | P23: 8 | Q23: [turn 0, user] please draw a chart comparing the confirmed positive COVID-19 cases, from January 2021 to 2023, for Europe Union, Hong Kong and China [turn 1, assistant] I'm an AI language model and I cannot directly draw charts, but I can provide you with the confirmed positive COVID-19 case numbers for the mentioned regions during January 2021 to 2023 if available. For a detailed and visual representation, I recommend visiting a reliable source like the official websites of World Health Organization (WHO), European Centre for Disease Prevention and Control (ECDC), or Our World in Data. However, it is important to note that my training data only goes up until September 2021, so I cannot provide you with accurate case numbers beyond that date. It's advisable to visit the sources mentioned above for the latest numbers. For the data available up until September 2021: European Union: January 2021: ~16 million confirmed cases September 2021: ~35 million confirmed cases Hong Kong: January 2021: ~9,000 confirmed cases September 2021: ~12,000 confirmed cases China: January 2021: ~88,000 confirmed cases September 2021: ~108,000 confirmed cases Keep in mind that the COVID-19 pandemic is still ongoing, and the numbers can change significantly. Make sure to verify the number of cases from official sources for the most accurate and updated information for your required time frame. [turn 2, user] could you do it a table format, month by month? [turn 3, assistant] Keep in mind that the data I provide is limited to my training data, which goes up until September 2021. For the most accurate and updated information, please visit the official websites of World Health Organization (WHO), European Centre for Disease Prevention and Control (ECDC), or Our World in Data. Here is a summary table of COVID-19 confirmed cases from January 2021 to September 2021 for the European Union, Hong Kong, and China: | European Union | Hong Kong | China ---------+----------------+-----------+------- January | 16,000,000 | 9,000 | 88,000 February | 20,000,000 | 10,500 | 90,000 March | 24,000,000 | 11,000 | 92,000 April | 27,000,000 | 11,500 | 94,000 May | 30,000,000 | 11,800 | 96,000 June | 32,000,000 | 11,900 | 99,000 July | 33,500,000 | 12,000 | 102,000 August | 34,500,000 | 12,100 | 105,000 September| 35,000,000 | 12,200 | 108,000 *Note: The numbers in this table are approximations based on available data up until September 2021. They may not be completely accurate, and numbers have likely changed since then. Please refer to the official sources, such as WHO or ECDC, mentioned earlier for the latest and most accurate information. [turn 4, user] please prepare the above data to Excel [turn 5, assistant] As an AI model, I cannot create excel files. However, you can quickly create an excel sheet from the provided information in my previous response. Here's how to input the data in Excel or any other spreadsheet software: 1. Open Excel or your preferred spreadsheet software. 2. Copy the following headers and paste them into the first row (A1, B1, C1, and D1 cells): ``` Month | European Union | Hong Kong | China ``` 3. Copy the following data and paste it into subsequent rows (starting from A2 cell): ``` January | 16000000 | 9000 | 88000 February | 20000000 | 10500 | 90000 March | 24000000 | 11000 | 92000 April | 27000000 | 11500 | 94000 May | 30000000 | 11800 | 96000 June | 32000000 | 11900 | 99000 July | 33500000 | 12000 | 102000 August | 34500000 | 12100 | 105000 September | 35000000 | 12200 | 108000 ``` Now you have the table with the data in Excel. Don't forget that my input data only goes up until September 2021. For the most updated and accurate information, please visit the official websites of World Health Organization (WHO), European Centre for Disease Prevention and Control (ECDC), or Our World in Data. [turn 6, user] Please provide the list of all the restrictions imposed in Hong Kong due to COVID-19 [turn 7, assistant] As of my last training update in September 2021, here is an overview of some restrictions imposed in Hong Kong due to COVID-19. Please note that these measures are subject to change, and you should consult official government sources for the most up-to-date information. 1. Entry restrictions and quarantine measures: Hong Kong limited entry to residents and required mandatory 14 to 21-day hotel quarantines for inbound travelers, with testing before and after the quarantine period. 2. Social distancing measures: Venues like bars, karaoke establishments, and nightclubs were temporarily closed. Restaurants had limited seating capacity and restricted dine-in hours. 3. Public gathering restrictions: Public gatherings were restricted to a certain number of people, with rules varying depending on the pandemic situation. 4. Wearing masks: Mandatory mask-wearing was required in public transportation, shopping malls, markets, and indoor and outdoor public spaces. 5. Work-from-home arrangement: Government workers, as well as private sector employees, were encouraged to work from home whenever possible. 6. Travel advisories: Citizens were advised to avoid non-essential international travel. 7. Closure of schools and universities: Schools and universities were closed for in-person classes at various points during the pandemic. Remote learning was implemented. 8. Health code systems: A health code system was implemented for tracking individuals' COVID-19 test results and vaccination status to facilitate travel and access to certain venues. 9. Testing and tracing: Voluntary and mandatory testing was conducted in high-risk areas, and contract tracing efforts were implemented to track and control the spread of the virus. 10. Restrictions on sports and recreation facilities: Some sports and recreational facilities were temporarily closed, with restrictions on usage when reopened. These measures may have changed since I last updated my knowledge, and the restrictions may be different today. It is essential to consult official government sources like the Hong Kong Special Administrative Region Government website (www.info.gov.hk) for the latest and most accurate information. | R23: Correct | S23: Correct
A24: 0c9cf834613feb7c0f48c88ad1ff38db | B24: TRUE | C24: TRUE | D24: TRUE | E24: PERSONAL | F24: CONSUMER_AND_PERSONAL_FINANCE | G24: CONSUMER_AND_PERSONAL_FINANCE | H24: PROCEDURE_HOWTO | I24: PROCEDURE_HOWTO | J24: FALSE | K24: 4 | M24: 4 | N24: low | O24: The user seeks practical steps for claiming a deceased mother's life-insurance policy, which is a personal insurance procedure rather than a request to draft legal text. | P24: 6 | Q24: [turn 0, user] write a professional response to Mr Hall the Gardaworld recruiter. answer his as affirmative. respond in the affirmative I have both a US passport and a valid state driver's license. [turn 1, assistant] Dear Mr. Hall, Thank you for considering me for the position at Gardaworld. I am pleased to inform you that I possess both a US passport and a valid state driver's license. I am confident that my qualifications align well with the requirements of the role and I am excited about the opportunity to potentially work with Gardaworld. Thank you again for considering my application. Sincerely, [Your Name] [turn 2, user] rewrite in a professional tone. Inform Mr Hall i do not have prior military experience. however i served as a Hampton sheriff's Deputy [turn 3, assistant] Dear Mr. Hall, Thank you for the opportunity to discuss my qualifications for the position at Gardaworld. While I do not have prior military experience, I have served as a Hampton Sheriff's Deputy. I believe that my experience in law enforcement has equipped me with the skills and knowledge necessary to succeed in this role. I appreciate your time and consideration. Sincerely, [Your Name] [turn 4, user] list the steps in order to redeem and claim a life insurance police. after the death of a mother. [turn 5, assistant] 1. Notify the insurance company: The first step is to inform the life insurance company about the death of the policyholder, in this case, the mother. You will need to contact the company and provide them with the necessary information, such as the policy number, date of death, and any other relevant details. 2. Obtain the death certificate: You will need to obtain a certified copy of the death certificate from the appropriate authorities. This document is crucial for the insurance company to process the claim. 3. Submit the claim form: The insurance company will provide you with a claim form that needs to be completed and submitted along with the death certificate and any other required documents. Make sure to provide accurate information to avoid any delays in processing the claim. 4. Wait for the claim to be processed: Once the claim form and all necessary documentation have been submitted, the insurance company will review the information and process the claim. This process may take some time, so it is important to be patient and follow up with the company as needed. 5. Receive the proceeds: Once the claim has been approved, the insurance company will release the proceeds to the designated beneficiaries, as specified in the policy. The beneficiaries will receive the death benefit payout in accordance with the terms of the policy. It is important to carefully review the policy details and understand the terms and conditions for claiming the life insurance proceeds after the death of a loved one. | R24: Correct | S24: Correct | T24: problem is that the legal question starts at turn #4 - > perhaps we can adjust this
A25: c1453a75a7cdb665da09a997a8f8d666 | B25: TRUE | C25: TRUE | D25: TRUE | E25: PROFESSIONAL | F25: BUSINESS_AND_COMMERCIAL | G25: BUSINESS_AND_COMMERCIAL | H25: RIGHTS_OPTIONS_ADVICE | I25: RIGHTS_OPTIONS_ADVICE | J25: FALSE | K25: 0 | M25: 0 | N25: medium | O25: The user asks whether Israeli law restricts institutions from carrying out a practical cross-border money transfer to the UAE. | P25: 2 | Q25: [turn 0, user] Is there any law preventing israeli institutions from sending money out of the country to the UAE? [turn 1, assistant] As an AI language model, I do not have access to the latest updates and changes in the law. However, as per the information available, there is no law preventing Israeli institutions from sending money out of the country to the UAE. The two countries established diplomatic ties in August 2020, and since then, numerous transactions and investments have taken place between them. However, it is always advisable to consult a legal expert or authority for updated information. | R25: Correct | S25: Correct
A26: 3fbba8bc8a91e61aa4c762ec3d826c25 | B26: FALSE | C26: TRUE | D26: FALSE | E26: GENERAL_CURIOSITY | H26: INFO_EXPLANATION | I26: INFO_EXPLANATION | J26: FALSE | M26: 12; 14 | N26: low | O26: The user raises a speculative, general-curiosity question about whether future space law might classify and regulate a spacecraft particle-beam defense as a weapon, without seeking guidance for a real or planned legal situation. | P26: 16 | Q26: [turn 0, user] WHen future spacecraft pass though the ISM what mittigation messures might be avalible for the mittgation of dust and gas bombardment of the Hull at near relitervistic or in the far future relitervistic speeds [turn 1, assistant] Mitigation measures for the bombardment of dust and gas on spacecraft hulls at near relativistic or far future relativistic speeds are highly speculative since such technologies are still in the realm of science fiction. However, some theoretical possibilities could be considered: 1. Active Plasma Shields: Creating a plasma shield around the spacecraft could ionize and vaporize incoming particles, reducing the impact of dust and gas bombardment. This could potentially deflect or vaporize smaller particles. 2. Magnetic Shielding: Utilizing strong magnetic fields may help deflect or repel charged particles, reducing their impact on the spacecraft hull. However, this may not be effective against neutral particles such as dust. 3. Electrostatic Shields: By charging the spacecraft hull with a specific voltage, an electrostatic shield could be created. This shield might repel or deflect charged particles, reducing their impact. 4. Advanced Materials: Development of ultra-strong and lightweight materials that are capable of withstanding high-energy impacts could be explored. These materials might be designed to absorb or disperse the energy of incoming particles. 5. Deflection Systems: Equipping spacecraft with advanced deflection systems could be employed to divert or steer away from debris or gas clouds. This may require highly advanced propulsion systems or gravitational manipulation techniques. It is important to note that these ideas are currently speculative and primarily based on theoretical concepts. Advancements in technology and our understanding of physics would be necessary to develop practical mitigation measures for dust and gas bombardment during near relativistic or far future relativistic space travel. [turn 2, user] What about Material Based on eith Graphite or Byrilliam as shielding [turn 3, assistant] Materials based on graphite or beryllium could potentially be used for shielding in spacecraft, although there are certain considerations to keep in mind: 1. Graphite: Graphite is a form of carbon that is known for its high thermal conductivity and strength. It is commonly used in heat shields due to its ability to withstand high temperatures. However, graphite may not be as effective in shielding against high-energy impacts from dust and gas particles. Its atomic structure might not provide sufficient strength to absorb or disperse the energy of fast-moving particles, which could lead to penetration or damage to the spacecraft hull. 2. Beryllium: Beryllium is a lightweight and strong metal that has excellent thermal conductivity as well. It is also used in some aerospace applications. Beryllium might offer better structural strength compared to graphite, and it has good shielding properties against certain types of radiation, such as X-rays and gamma rays. However, its effectiveness in shielding against high-energy dust or gas particles would depend on the specific properties and thickness of the beryllium material. While graphite and beryllium may have some shielding attributes, it is important to remember that protecting against high-energy impacts at relativistic speeds would likely require advanced materials or shielding concepts that have not yet been fully explored or developed. These materials would need to possess exceptional strength, resilience, and the ability to dissipate or deflect the extreme forces generated by fast-moving particles. [turn 4, user] With Active Plasma Shields: how do you pritect the spacecraft from the plasma hulll interface [turn 5, assistant] Protecting the spacecraft from the plasma hull interface in the context of active plasma shields is indeed an important consideration. Here are a few potential approaches: 1. Magnetic Field Containment: The active plasma shield could generate a magnetic field that contains and confines the plasma around the spacecraft. This magnetic field would need to be strong enough to prevent the plasma from contacting the spacecraft hull directly. By controlling the magnetic field strength and shape, the plasma can be contained at a specific distance from the hull, reducing any potential damage. 2. Electric Field Manipulation: By utilizing an electric field generated by the active plasma shield, it might be possible to control the movement and orientation of the plasma. The electric field could manipulate the charged particles within the plasma, guiding them away from the spacecraft hull and maintaining a distance between the plasma and the hull. 3. Ionization Control: An active plasma shield could selectively ionize particles in the surrounding environment, creating a plasma buffer zone. This buffer zone of ionized particles could act as a transitional layer between the spacecraft hull and the plasma, minimizing direct contact and potential damage. 4. Plasma Deflection: The active plasma shield could produce localized plasma streams directed away from the spacecraft hull. These streams could be carefully managed and adjusted to create a sort of "plasma sheath" that surrounds the spacecraft, protecting it from direct contact with the bulk plasma. It is worth noting that these are hypothetical approaches that rely on advanced technologies and knowledge that do not currently exist. The implementation of active plasma shields and their protection against the plasma hull interface would require significant advancements in plasma physics, magnetic fields, and control systems. [turn 6, user] What about the potental for the shild cuasing and implosion is the presure density is high enough [turn 7, assistant] If the pressure density generated by an active plasma shield is high enough, there is indeed a potential for implosion. This possibility arises due to the balance between the plasma pressure and the external pressure acting on the shield. It is crucial to carefully manage the plasma properties and containment to prevent any disruptive implosions. Here are a few considerations: 1. Structural Integrity: The spacecraft hull and the active plasma shield should be designed with robust structural integrity to withstand the pressure differentials that may arise. The materials used should be able to withstand the high pressures without deforming or collapsing. 2. Pressure Gradient Control: A careful control strategy is necessary to maintain a suitable pressure gradient between the external environment and the plasma shield. The design should ensure that pressure fluctuations are managed effectively to avoid sudden implosions or collapses. 3. Active Monitoring and Adjustment: Continuous monitoring of the pressure and density within the plasma shield is crucial. If pressure differentials become too extreme, adjustments can be made to maintain stability. Active control systems would need to continuously assess and regulate the shield's performance. Developing an active plasma shield that can withstand the internal and external pressure differentials without implosion is a significant engineering challenge. It would require extensive research, advanced computational models, precise control systems, and robust materials. The potential for implosion highlights the need for comprehensive analysis and careful design to ensure the shield's effectiveness and safety in real-world scenarios. [turn 8, user] you mentioned Deflection Systems [turn 9, assistant] Yes, deflection systems could be considered as a potential mitigation measure for dust and gas bombardment on spacecraft hulls. Here are a few possible approaches for deflection systems: 1. Electrostatic Deflection: Utilizing electric fields, the spacecraft could be equipped with electrodes or arrays that generate electric charges to repel charged particles away from the hull. By selectively inducing charges on specific areas or utilizing electrodes strategically, it may be possible to deflect particles and redirect them away from the spacecraft. 2. Magnetic Deflection: Employing strong magnetic fields, either generated by onboard magnets or utilizing a magnetic sail concept, could deflect charged particles, particularly in the form of ions or plasma. By manipulating magnetic fields alongside careful spacecraft orientation, the charged particles could be diverted away from the hull. 3. Particle Beam Deflection: Another approach could involve the deployment of particle beams from the spacecraft. This beam, consisting of charged particles or neutral particles, could be aimed at the incoming dust or gas cloud, causing interactions that alter the trajectory or break up the cloud, reducing the impact on the spacecraft hull. 4. Force Fields: Fictional science has often depicted the use of force fields as a defense mechanism. Although such technology does not currently exist, force fields, created by generating energy barriers or plasma shields around the spacecraft, could potentially repel or absorb the impact of dust and gas particles. It's important to note that these deflection systems are currently theoretical and speculative. Their feasibility and effectiveness at near relativistic or far future relativistic speeds would require significant advancements in technology and a deeper understanding of the physical principles involved. [turn 10, user] Force Feilds I'm not sure thouse will work in reality: I am looking towards more realistic options [turn 11, assistant] You are correct that force fields, as commonly depicted in science fiction, are not yet a realistic option for spacecraft protection. In that case, let's focus on more realistic options: 1. Shielding Materials: Using advanced materials with high strength and durability could provide a passive form of protection against dust and gas bombardment. Materials such as composites, ceramics, or advanced alloys could be specifically designed to withstand high-energy impacts and minimize damage to the spacecraft hull. 2. Whipple Shields: The Whipple shield design is a proven technique used in existing spacecraft to protect against micrometeoroids. It consists of multiple layers of thin metal sheets or other lightweight materials with spacing between them. When particles impact the outer layer, they disintegrate or vaporize, dissipating their energy and reducing the impact on subsequent layers. 3. Active Debris Tracking and Avoidance: Employing advanced sensors and detection systems, spacecraft could actively track and avoid regions of high particle density or gas clouds. By maneuvering the spacecraft to safer trajectories, the risk of encountering dense regions of dust and gas could be minimized. 4. Baffles and Aerogels: Baffles, such as physical obstacles or deployable shields placed strategically on the spacecraft, can help divert or redirect incoming particles away from the hull. Additionally, lightweight materials like aerogels, with their low density and high porosity, can passively absorb and slow down particles before they reach the spacecraft hull. 5. Mission Planning and Route Optimization: Thorough mission planning that takes into account the interstellar or intergalactic environment can help avoid regions with known high dust or gas densities. Optimizing the spacecraft's route to minimize the exposure to interstellar medium can reduce the risk of dust and gas bombardment. While these options are more realistic, it's important to note that mitigating dust and gas bombardment at near or far relativistic speeds is an extreme engineering challenge that requires advancements in various fields. Therefore, continued research and technological development are necessary to achieve effective mitigation measures in the future. [turn 12, user] How practical (tecnologicaly speaking) would your partical beam option be from an energy usage and realtime targeting perspective [turn 13, assistant] Implementing a particle beam deflection system for spacecraft protection would indeed pose significant technological challenges, particularly in terms of energy usage and real-time targeting. Here are some considerations: 1. Energy Requirements: Generating and sustaining a particle beam for deflection purposes would require a substantial amount of energy. The spacecraft would need to carry sufficient power sources, such as advanced batteries, nuclear reactors, or other high-energy-density systems, to supply the necessary energy for the particle beam. 2. Real-Time Targeting: To effectively deflect incoming particles, the particle beam system would need to quickly and accurately track the trajectory of the particles in real-time. Sophisticated sensor systems, such as advanced cameras or lidar, would be required to provide accurate data about the approaching particles. Additionally, precise targeting algorithms and control systems would need to be in place to adjust the beam's direction and intensity. 3. Particle Interactions: When the particle beam interacts with the dust or gas cloud, various physical processes may occur, such as charging, fragmentation, or vaporization. These interactions would need to be thoroughly understood to ensure that the desired deflection or dispersion is achieved. Modelling and simulations would play a crucial role in optimizing the particle beam's parameters for effective deflection. 4. Payload and Size Constraints: The size and mass of the particle beam system, including the necessary energy storage, sensors, targeting systems, and beam generators, would need to be considered within the payload and launch mass constraints of the spacecraft. The system should be designed to minimize weight and size while maximizing overall efficiency. It is important to note that the practicality of a real-time particle beam deflection system highly depends on future technological advancements and breakthroughs in energy generation, miniaturization, targeting accuracy, and control systems. Currently, these challenges remain significant hurdles for the practical implementation of such a system on spacecraft. [turn 14, user] Woulden' any spacelaw worthy of the name consider such a system as a weapons system and either heavely regulate it of prehaps ban it altogether, its design maybe for ship saftey but maybe considered dual use, at least from a regulatory perspective. [turn 15, assistant] You raise an important point regarding the regulatory perspective and the consideration of a particle beam deflection system as a potential weapons system. In the realm of space law, the concept of dual-use technologies, which have both civilian and military applications, is indeed a significant factor in determining regulations and restrictions. If a particle beam deflection system is designed solely for the purpose of spacecraft safety and protection from dust and gas bombardment, it is conceivable that regulations could be put in place to ensure its use is limited to peaceful purposes. International treaties and agreements, such as the Outer Space Treaty, have provisions that promote the peaceful exploration and use of outer space. However, it is also plausible that if a particle beam deflection system has the potential for use as a weapon, it could be subject to strict regulations or even prohibition under certain arms control agreements or other space governance frameworks. The classification of such systems as weapons would likely depend on the specific characteristics, capabilities, and intended use. Ultimately, the development and deployment of any space technology, including particle beam deflection systems, would need to comply with applicable national and international regulations and agreements. The regulatory approach would likely involve a careful evaluation of the system's capabilities, intent, and potential security implications to ensure that it aligns with the principles of peaceful exploration and use of outer space. | R26: Correct | S26: Correct
A27: 14e4fad71abf409a2d77d6700c9ee273 | B27: FALSE | C27: FALSE | D27: TRUE | E27: PERSONAL | J27: FALSE | M27: 2; 4; 6; 8 | N27: low | O27: The user seeks practical technical help setting up free Azure-based job-posting notifications, with no legal issue or request. | P27: 10 | Q27: [turn 0, user] hi [turn 1, assistant] Hello! How can I assist you today? [turn 2, user] I want an email notification whenever any company posts a new job [turn 3, assistant] Creating an automated email notification for new job postings from any company involves several steps and tools, depending on where these jobs are posted and the technical options available. Various job platforms and company websites offer different methods for staying updated. Here's a general guide to setting up notifications: ### Job Boards and Aggregator Sites Major job boards and job aggregator sites like Indeed, LinkedIn, Glassdoor, and Monster offer built-in alert systems. Here’s how you can typically set them up: 1. **Create an Account:** Most websites require you to create an account to set up job alerts. 2. **Search for Jobs:** Perform a search using keywords that match the type of jobs and companies you're interested in. You can often filter by location, job type (full-time, part-time, etc.), and other criteria. 3. **Set Up Alerts:** Look for an option to “Create Alert” or “Get Job Notifications” on the search results page. This option might sometimes be represented by a bell icon or something similar. 4. **Specify Alert Frequency:** You'll usually be asked how often you want to receive these alerts (e.g., daily, weekly). ### Using Google Alerts For companies or job types not well-represented on major job boards, or to cast a wider net, Google Alerts is a versatile tool: 1. Go to [Google Alerts](https://www.google.com/alerts). 2. In the “Create an alert about” box, enter keywords related to the jobs and companies you are interested in. You might use a formula like "company name + careers" or "job title + location". 3. Click on “Show options” to adjust the frequency, sources, language, region, and how many results you want to get. 4. Choose “Automatic (by default)” under “Deliver to” to receive alerts via email. 5. Click “Create Alert”. ### Using IFTTT (If This Then That) For more specific or complex needs, IFTTT can link various web services to send you emails about new job postings. This might require a combination of RSS feeds from company career pages and the Email service on IFTTT: 1. **Sign Up/Login to IFTTT:** Visit [IFTTT](https://ifttt.com/) and either sign up for a new account or log in. 2. **Create a New Applet:** Go to your profile, select “Create” or “New Applet”, then click on “If This” to choose a trigger. You might select an RSS feed from a company’s career page as the trigger. 3. **Choose a Service for ‘This’**: For job postings, you could select “RSS Feed” and then “New feed item”. 4. **Fill in the Feed URL**: Input the RSS feed URL from the targeted company's career page. 5. **Choose ‘That’** to set the action: Select “Email” and then “Send me an email”. 6. **Complete the Setup**: Customize the email template as needed and then finish the setup. ### Remember: - Privacy: Be mindful of privacy and what information you share when setting up alerts. - Specificity: The more specific your keywords and filters, the more relevant your alerts will be. - Maintenance: Periodically review your alerts to adjust or remove them as your job search needs change. By using these techniques, you can automate much of the process of finding out about new job postings. However, remember no system is perfect—consider checking in on these websites and your alerts occasionally to ensure you're not missing out. [turn 4, user] how to do this using Azure [turn 5, assistant] To set up job notification emails for new job postings from various companies using Azure, you would ideally leverage a combination of Azure services such as Azure Logic Apps, Azure Functions, and possibly the Bing Search API for gathering job posting information. This setup can automate the process and send you email notifications. Below is a high-level approach to achieving this. ### Step 1: Set Up Azure Services First, you'll need to have an Azure account. If you don't already have one, you can create one at [Azure’s official website](https://azure.microsoft.com/). ### Step 2: Choose a Data Source Decide where you want to source job postings from. For this explanation, let’s assume you use a job board's API or web scraping (with permission) to collect job postings. Alternatively, if you're focusing on specific companies, you might use their careers page RSS feeds (if available) or directly use the Bing Search API to retrieve job postings. ### Step 3: Use Azure Logic Apps to Automate Data Retrieval and Email Notification Azure Logic Apps provides a way to automate workflows and integrate services. You can use it to periodically check for new job postings and send email notifications. 1. **Create a Logic App**: In the Azure portal, create a new Logic App. 2. **Define the Trigger**: The trigger could be a schedule (e.g., check daily), an HTTP request (if you're triggering this via a web call), or an event (like a new item in an RSS feed). - For **RSS Feeds**, you can use the "When a feed item is published" RSS connector as a trigger. - For **APIs**, you may use the HTTP trigger to make requests to job board APIs. 3. **Add an Action to Process Data**: Depending on your data source, this might involve parsing JSON from an API response or processing the details from an RSS feed. Use built-in Logic App functions and actions to filter or process this data to your needs. 4. **Set Up Bing Search API** (if applicable): If you're using the Bing Search API to find new job postings, set it up in Azure, and call it from your Logic App to search for job postings based on your criteria. 5. **Add an Action to Send Emails**: Once you have identified new job postings, add an action to send an email. You can use the built-in "Send an email" actions from connectors like Office 365 Outlook, Outlook.com, or Gmail etc., to send the notification. Configure the email details, including subject, body (you can list job posting details here), and recipient. ### Step 4: Monitor and Adjust Once your Logic App is running, monitor its execution and results. You might need to adjust filters, keywords, or logic based on the job postings you're receiving. ### Additional Considerations: - **Costs**: Be aware of the costs associated with Azure services and API calls, especially if you're making a large number of API requests. - **Rate Limiting**: Both the job board APIs and the Bing Search API have rate limits. Ensure your application respects these limits to avoid being blocked. - **Permissions**: If you're scraping websites for job postings, ensure you comply with their robots.txt file and terms of service to avoid legal issues. This setup provides a highly customizable and scalable way to automate job notification emails. With Azure Logic Apps, much of the heavy lifting is abstracted away, allowing you to focus on fine-tuning your workflow to match your job-seeking needs. [turn 6, user] if i want this for free? [turn 7, assistant] If you're looking for a free solution to set up job notification emails for new postings, you'll need to leverage free tools and services, avoiding paid options like Azure. Here’s a strategy using free tools: ### Option 1: Use Job Board Alerts and Google Alerts The simplest and most straightforward way is to utilize the built-in alert systems of major job boards (Indeed, LinkedIn, Glassdoor, etc.) and Google Alerts. - **Job Boards**: Sign up and use their "Alert" feature to get emails for new postings based on your search criteria. - **Google Alerts**: Set up alerts for new web results related to job postings. For example, you can create an alert for “Software Developer jobs at Company XYZ” or “New marketing positions in Chicago”. ### Option 2: IFTTT for Custom Alerts If This Then That (IFTTT) is a web-based service that allows you to create chains of conditional statements (applets) and can be used for monitoring job postings on certain websites and triggering email notifications. 1. **Sign Up for IFTTT**: Visit [IFTTT](https://ifttt.com/) and create an account. 2. **Create a New Applet**: Choose a trigger, such as an RSS feed update from a company’s career page. 3. **Choose an Action**: Set an email to be sent to you whenever the trigger condition is met. You can customize the email content with details from the trigger. ### Option 3: Use Google Sheets with Google Apps Script For more customization, you can use Google Sheets combined with Google Apps Script to periodically check job boards or company websites (that you have legal permission to scrape), and send an email when new jobs are found. 1. **Create a Google Sheet**: To manage URLs and job titles. 2. **Script Editor**: - Open Google Sheets, click on `Extensions` > `Apps Script`. - Write a custom script to fetch data from job boards or websites. Use `UrlFetchApp` for making HTTP requests and parsing the response. - Use the MailApp service (`MailApp.sendEmail()`) to send an email when new jobs matching your criteria are found. 3. **Triggers**: Set up a time-driven trigger to automatically run your job search script at regular intervals. ### Option 4: GitHub Actions for Advanced Users If you're technically inclined, you can use GitHub Actions to run a script that checks for job postings and sends an email notification. GitHub Actions allows scheduled tasks (cron jobs) in a free tier. 1. **Create a GitHub Repository**: Store your code/script. 2. **Set Up GitHub Actions**: Define a workflow in `.github/workflows` that runs on a schedule. Use actions like `actions/checkout` to check out your code and custom scripts to fetch job postings. 3. **Email Notification**: You can use third-party actions to send emails or use a serverless function (e.g., an endpoint you expose via Vercel or Netlify that sends an email). ### Considerations - **Privacy**: Be cautious about where and how you share your personal information. - **Legality**: Ensure you’re allowed to scrape a website for information if you choose that route. Respect `robots.txt` and terms of use. - **Limits**: Free tools may have usage limits or limitations on functionality. Be aware of these and plan accordingly. Using these free tools and services can effectively keep you informed of new job postings without incurring costs, though they may require more setup and maintenance effort than a paid solution. [turn 8, user] Option2 [turn 9, assistant] If you're interested in using IFTTT (If This Then That) for setting up custom job notification emails for free, you'll be leveraging its ability to connect different web services and perform actions based on triggers. Here’s how you can use IFTTT to set up alerts for new job postings: ### Step 1: Create an Account on IFTTT - If you haven't already, go to the [IFTTT website](https://ifttt.com/) and sign up for an account. ### Step 2: Explore Existing Applets - Once logged in, explore existing applets by searching for keywords related to job notifications, RSS feeds, or email notifications. It's possible that you might find a pre-existing applet that suits your needs. ### Step 3: Create a New Applet If you can’t find an existing applet that meets your requirement or you want something custom, follow these steps to create a new applet: 1. **Go to Your Profile**: Click on your profile icon and choose “Create” to start a new applet. 2. **Set up the Trigger (This)** - Click on “+This” to set what triggers the applet. - For job notifications, you might want to choose **RSS Feed** if you're monitoring a specific company's job feed, or **Webhooks** for more complex triggers. - If you selected **RSS Feed**, choose “New feed item” and enter the RSS feed URL of the job board or company career page. 3. **Set up the Action (That)** - Click on “+That” to choose the action that happens when the trigger occurs. - Search for an **Email** service. IFTTT supports sending emails as actions. Choose “Send me an email”. - Configure the email action. You can customize the email subject and body to include details from the RSS feed item, such as the job title, description, and link. 4. **Complete and Name Your Applet** - Give your applet a descriptive name and review your settings. - Click “Finish” to save and activate your applet. ### Step 4: Monitor and Adjust - Your new applet will run according to the triggers you’ve set. It's a good practice to monitor its performance and make adjustments as needed. For example, if you're getting too many unrelated job alerts, you might need to refine the RSS feed or the keywords. ### Additional Tips - **RSS Feeds**: Not all websites offer RSS feeds for their job postings. In cases where they don't, you might have to look for alternative sources or use web scraping techniques (with caution and permission). - **Expanding Beyond IFTTT**: If your job searching or notification needs become complex, you might look into combining IFTTT with other services or even writing custom scripts hosted on platforms like GitHub Actions, as mentioned in Option 4. - **Stay Organized**: If you’re monitoring multiple job sources, it might be helpful to use different email addresses or set up email filters to categorize and prioritize job alerts. By leveraging IFTTT's straightforward interface and wide array of service connections, you can set up a versatile job notification system without any costs. This can save time in your job search process and ensure you’re among the first to know about new opportunities. | R27: Correct | S27: Correct
A28: 3b79892b6be97c1189561d5779efcde0 | B28: TRUE | C28: TRUE | D28: TRUE | E28: PROFESSIONAL | F28: TAX_LAW | G28: TAX_LAW | H28: RIGHTS_OPTIONS_ADVICE | I28: INFO_EXPLANATION; RIGHTS_OPTIONS_ADVICE | J28: FALSE | K28: 4 | M28: 2; 4; 6 | N28: low | O28: The user seeks practical tax-identification guidance for operating as an Amazon affiliate in Saudi Arabia, including whether a TIN is required and what identifier a Saudi national should provide. | P28: 8 | Q28: [turn 0, user] I would like to come up with a name for a blog that has the meaning "reading and musings", I want to change the word reading though. WHat should I use instead? [turn 1, assistant] Here are some potential alternatives for "reading": 1. Lit (short for literature) 2. Books 3. Stories 4. Pages 5. Prose 6. Narratives 7. Texts 8. Novels 9. Chronicles 10. Sagas Combining any of these words with "musings" could create a unique and memorable blog name. For example: "Lit Musings", "Pages and Musings", or "Sagas in Mind". [turn 2, user] Does saudi arabia have a TIN? [turn 3, assistant] Yes, Saudi Arabia has a Tax Identification Number (TIN), which is called a "Unified Identification Number" (ID) or in Arabic "رقم الهوية الموحد" (Raqm al-Huwia al-Muwahhad). The TIN is issued by the General Authority of Zakat and Tax (GAZT) to individuals and entities subject to tax in Saudi Arabia. The TIN is used to identify taxpayers, including residents and non-residents, for tax purposes. [turn 4, user] As an amazon affiliate in Saudi Arabia, do I need to provide a TIN? [turn 5, assistant] Yes, as an Amazon affiliate in Saudi Arabia, you may need to provide a Tax Identification Number (TIN) if you are subject to tax in Saudi Arabia. The TIN is used by the General Authority of Zakat and Tax (GAZT) to identify tax obligations for individuals and entities in Saudi Arabia, including Amazon affiliates. It is important to consult with a tax professional or the GAZT to determine whether or not you need a TIN if you are earning income from your Amazon affiliate activities in Saudi Arabia. [turn 6, user] What is the TIN for a Saudi national that wants to be an amazon affiliate? [turn 7, assistant] If you are a Saudi national who wants to become an Amazon affiliate, you will need to provide your Tax Identification Number (TIN), which is called a "Unified Identification Number" (ID) or in Arabic "رقم الهوية الموحد" (Raqm al-Huwia al-Muwahhad). The TIN is issued by the General Authority of Zakat and Tax (GAZT) to individuals subject to tax in Saudi Arabia. If you do not have a TIN, you can apply for one through the GAZT website or by visiting a GAZT branch. You will need to provide your national identity card and other relevant documents to obtain the TIN. Once you have obtained your TIN, you can use it to register as an Amazon affiliate in Saudi Arabia and receive commissions on sales made through your affiliate links. | R28: Correct | S28: Correct | T28: starts after turn #2
A29: 944ea8ed4acdd74f6e47049a1b040362 | B29: FALSE | C29: FALSE | D29: TRUE | E29: PROFESSIONAL | J29: FALSE | M29: 0 | N29: low | O29: The user requests Midjourney image prompts and does not discuss law or seek any legal guidance or drafting. | P29: 2 | Q29: [turn 0, user] As a prompt generator for a generative AI called "Midjourney", you will create image prompts for the AI to visualize. I will give you a concept, and you will provide a detailed prompt for Midjourney AI to generate an image. Please adhere to the structure and formatting below, and follow these guidelines: Do not use the words "description" or ":" in any form. Do not place a comma between [ar] and [v]. Write each prompt in one line without using return. Structure: [1] = Night view of the bus open-air bar in front of the hotel [2] = a detailed description of [1] with specific imagery details. [3] = a detailed description of the scene's environment. [4] = a detailed description of the compositions. [5] = a detailed description of the scene's mood, feelings, and atmosphere. [6] = A style (e.g. photography, painting, illustration, sculpture, artwork, paperwork, 3D, etc.) for [1]. [7] = a detailed description of the scene's mood, feelings, and atmosphere. [ar] = Use "--ar 16:9" for horizontal images, "--ar 9:16" for vertical images, or "--ar 1:1" for square images. [v] = Use "--niji" for Japanese art style, or "--v 5" for other styles. Formatting: Follow this prompt structure: "/imagine prompt: [1], [2], [3], [4], [5], [6], [7], [ar] [v]". Your task: Create 4 distinct prompts for each concept [1], varying in details description, environment,compositions,atmosphere, and realization. Write your prompts in english. Do not describe unreal concepts as "real" or "photographic". Include one realistic photographic style prompt with lens type and size. Separate different prompts with two new lines. Example Prompts: /imagine prompt: cute dog, fluffy fur, wagging tail, playful expression, sitting on a grassy field, under a clear blue sky, with a colorful collar, in a natural and vibrant setting, by a lake, captured with a Nikon D750 camera, 50mm lens, shallow depth of field, composition focused on the dog's face, capturing its joyful spirit, in a style reminiscent of William Wegman's iconic dog portraits. --ar 1:1 --v 5.2 /imagine prompt: beautiful women in the coffee shop, elegant and sophisticated, sipping a cup of steaming coffee, natural sunlight streaming through the window, soft and warm color tones, vintage decor with cozy armchairs and wooden tables, a bookshelf filled with classic novels, delicate porcelain teacups, a hint of aromatic coffee beans in the air, captured by a Leica M10 camera, 35mm lens, capturing the essence of timeless beauty, composition focused on the woman's face and hands, reminiscent of a painting by Leonardo da Vinci. --ar 1:1 --v 5.2 /imagine prompt: A captivating Halo Reach landscape with a Spartan amidst a battlefield, fallen enemies around, smoke and fire in the background, emphasizing the Spartan's determination and bravery, detailed environment blending chaos and beauty, Illustration, digital art, --ar 16:9 --v 5 [turn 1, assistant] /imagine prompt: Night view of the bus open-air bar in front of the hotel, colorful lights illuminating the scene, people enjoying drinks and conversation, soft music playing in the background, the bar counter filled with glasses and bottles, a bartender skillfully preparing cocktails, a canopy above the bar protecting guests from the rain, a cozy seating area with comfortable cushions and warm lighting, surrounded by lush greenery, creating a vibrant and lively atmosphere. --ar 16:9 --v 5.2 /imagine prompt: Night view of the bus open-air bar in front of the hotel, a stunning city skyline as the backdrop, skyscrapers lit up in neon lights, reflections shimmering on the water, people gathered around the bar, laughter and clinking glasses filling the air, a variety of drinks with colorful garnishes and unique flavors, the bar counter made of reclaimed wood, decorated with quirky signs and vintage posters, creating a trendy and hip setting. --ar 16:9 --v 5.2 /imagine prompt: Night view of the bus open-air bar in front of the hotel, located on a beach, palm trees swaying in the breeze, the sound of crashing waves filling the air, a cozy bonfire nearby, people sitting on wooden stools around the bar, enjoying tropical cocktails adorned with umbrellas and fresh fruits, the bar counter made of bamboo, adorned with seashells and driftwood, creating a laid-back and beachy vibe. --ar 16:9 --v 5.2 /imagine prompt: Night view of the bus open-air bar in front of the hotel, set in a mountainous region, stars twinkling in the clear sky, a cozy fireplace nearby, people huddled around the bar, sipping on warm and comforting drinks, the bar counter made of rustic wood, adorned with antlers and vintage lanterns, a breathtaking view of the snow-covered peaks in the distance, creating a cozy and intimate atmosphere. --ar 16:9 --v 5.2 | R29: Correct | S29: Correct
A30: db8296e8947e13acc1851fd8e79fcf47 | B30: FALSE | C30: TRUE | D30: TRUE | E30: PERSONAL | H30: DOCUMENT_DRAFTING | I30: DOCUMENT_DRAFTING | J30: TRUE | L30: 0 | M30: 0 | N30: low | O30: The user asks to draft a civil complaint about a cup-throwing incident but does not request substantive legal guidance. | P30: 2 | Q30: [turn 0, user] Draft a complaint, T vs M, suing for 2 dollars over plastic cup being thrown at T. [turn 1, assistant] IN THE COURT OF COMMON PLEAS YOUR COUNTY, [YOUR STATE] T,) Plaintiff, ) ) vs. ) Case No. ________ ) M, ) Defendant. ) ______________________________________) COMPLAINT GETTING COMES NOW the Plaintiff, T, by and through his/her attorney, and for the cause of action against the Defendant, M, states as follows: PARTIES 1. Plaintiff T (hereinafter, "T") is an adult invididual residing at [address], City of [city], State of [state]. 2. Defendant M (hereinafter, "M") is an adult individual residing at [address], City of [city], State of [state]. FACTUAL ALLEGATIONS 3. On or around of [date], M intentionally, maliciously, and without provocation, threw a plastic cup towards T, hitting T on the head and causing T both physical and emotional injuries. 4. As a direct and proximate result of M's irresponsible and malicious act, T suffered pain, humiliation, and emotional distress in the presence of their mutual friends and acquaintances. 5. T has informed M on numerous occasions about the damages suffered as a result of M's actions, and requested compensation for the same, but despite repeated requests, M has refused to pay any compensation to T. COUNT I: NEGLIGENCE 6. The Plaintiff incorporates by reference paragraphs 1 through 5 as if fully restated herein. 7. M owed a duty of care to T to act in a reasonable manner and not cause physical or emotional harm to T. 8. M breached the duty of care by negligently and intentionally throwing a plastic cup towards T and causing unwanted physical harm and emotional distress. 9. As a direct and proximate result of M's negligence, T has suffered physical pain and emotional distress in the amount of $2.00. COUNT II: ASSAULT 10. The Plaintiff incorporates by reference paragraphs 1 through 5 as if fully restated herein. 11. M's act of throwing the plastic cup towards T was committed with the intent to cause a reasonable apprehension of imminent harmful or offensive contact. 12. As a direct and proximate result of M's assault, T has suffered emotional distress in the amount of $2.00. WHEREFORE, Plaintiff, T, demands judgment as follows: a. The Defendant, M, shall pay to the Plaintiff, T, the sum of $2.00 as compensation for the physical pain and emotional distress suffered as a result of M's actions; b. The Defendant, M, shall pay to the Plaintiff, T, his/her costs of court and any other reasonable costs associated with this action; c. The court grant any other relief deemed just and proper. Respectfully submitted, ____________________________ [Your Name] Plaintiff, Pro Se [Your Address] [City, State, Zip Code] [Phone Number] [Email Address] | R30: Correct | S30: Correct
A31: aba8c3532dcfde224ba12ae53bd84bb5 | B31: FALSE | C31: FALSE | D31: TRUE | E31: PROFESSIONAL | J31: FALSE | M31: 0; 2; 4 | N31: low | O31: The user requests ordinary business correspondence to petroleum companies about opening a petrol station, without asking about laws, legal rights, licensing requirements, or legally operative documents. | P31: 6 | Q31: [turn 0, user] i need to write a latter to BYCO pakistan limited , about there late oil supply problem , i wait 1 year for there problem , now i want to see another company [turn 1, assistant] [Your Name] [Your Address] [City, State, ZIP] [Email Address] [Phone Number] [Date] BYCO Pakistan Limited [Company Address] [City, State, ZIP] Subject: Request for Alternative Oil Supplier Dear Sir/Madam, I hope this letter finds you well. I am writing to discuss a matter that has been of great concern to me. For the past year, I have been experiencing significant delays in the oil supply from BYCO Pakistan Limited. Despite patiently waiting for a resolution to this issue, no satisfactory progress has been made, which has left me with no option but to explore alternative suppliers for our oil requirements. As you are aware, uninterrupted and timely supply of oil is essential for the smooth functioning of my business operations. Unfortunately, the consistent delays and lack of communication regarding the reasons behind the late oil supply have severely impacted my business's productivity and overall performance over the past year. I understand that unforeseen circumstances can arise, affecting the supply chain of any company. However, it is crucial for suppliers to maintain open lines of communication with their clients regarding such issues and actively work towards resolving them in a timely manner. Regrettably, I feel that BYCO Pakistan Limited has not demonstrated a satisfactory level of commitment or urgency to rectify this unfortunate situation. Considering the significant negative impact on my business operations, I have been left with no choice but to seek an alternative supplier for my oil requirements. It is not my intent to terminate our business relationship with BYCO Pakistan Limited permanently, as I appreciate the history of our partnership and the overall quality of your products. Nonetheless, until the ongoing issues are adequately addressed and resolved, I have no option but to explore alternative options to ensure the sustainability of my own business. I kindly request BYCO Pakistan Limited to urgently address this matter and provide me with a clear plan of action to rectify the situation. Timely and consistent oil supply is crucial to meet the demands of my business and retain the faith of my clients. Furthermore, I would appreciate regular updates concerning any improvements, as this will help me evaluate whether I can continue to rely on BYCO Pakistan Limited for my oil supply needs in the future. Thank you for your attention to this matter. I am hopeful that my concerns will be promptly addressed and that we can find a mutually agreeable solution. I remain open to discussing this matter further and will be available at your convenience to arrange a meeting or schedule a call. Yours sincerely, [Your Name] [turn 2, user] i want to open petrol pump in District ghanche khaplu gilgit baltistan , district has around 200000 people , and demand of oil is day bay increasing , and people of khaplu is suffering form last 10 years becouse of short oil supply , so would you please wirte a later to attcok company [turn 3, assistant] [Your Name] [Your Address] [City, State, ZIP] [Email Address] [Phone Number] [Date] ATTACK Company [Company Address] [City, State, ZIP] Subject: Request for Petrol Pump in District Ghanche, Khaplu, Gilgit-Baltistan Dear Sir/Madam, I hope this letter finds you in good health. I am writing to express my interest and herein propose the establishment of a petrol pump in District Ghanche, Khaplu, Gilgit-Baltistan. The district is home to approximately 200,000 residents, and with the increasing demand for oil, the absence of a reliable fuel supply has caused significant distress among the people of Khaplu for the past ten years. District Ghanche, being a remote region in Gilgit-Baltistan, has been deprived of adequate oil supply for an extended period. This scarcity has adversely affected the daily lives and economic activities of the people residing in this area. Despite the efforts of the local authorities and residents, there have been no viable solutions that can cater to the increasing demand for oil products efficiently. Considering the population size and the evident need for a reliable source of fuel in District Ghanche, the establishment of a petrol pump in the area would be highly beneficial for the local community. It would not only alleviate the prevailing scarcity issue but also contribute significantly to the overall development and progress of the region. Therefore, I kindly request ATTACK Company to consider this proposal and invest in the establishment of a petrol pump in District Ghanche, Khaplu. By doing so, ATTACK Company can tap into a new market, while simultaneously helping to ease the plight of the people who have been adversely affected by the oil supply shortage. The strategic location of District Ghanche, along with its increasing population and demand for oil, presents a promising business opportunity for ATTACK Company. Establishing a petrol pump in this region would not only fulfill the fuel needs of the local inhabitants but also attract customers from neighboring areas, thereby creating a sustainable business venture. Furthermore, I assure you that the local administration and residents are prepared to lend their complete cooperation and support in facilitating the establishment of the petrol pump. All necessary legal requirements and permits would be obtained promptly, in accordance with local regulations and guidelines. I kindly request ATTACK Company to seriously consider this proposal, as it would not only contribute to the economic development of the region but also help improve the lives of the people of District Ghanche. I am available at your convenience to discuss this matter further or provide any additional information that may be required. Thank you for your attention to this matter. I look forward to a positive response, and I am hopeful that ATTACK Company will consider the potential benefits and seize this opportunity to make a significant impact on the lives of the people in District Ghanche, Khaplu. Yours sincerely, [Your Name] [turn 4, user] i would like to write a later to APL pakistan limited ,i want to open patrol pump in khaplu center district ghancehe , papulation of khaplu is around 70 thousand , and district papulation is 20000 .all this peoples are depending only 1 patrol pump. so i would like to open a new pump with Apl pakistan , [turn 5, assistant] [Your Name] [Your Address] [City, State, ZIP] [Email Address] [Phone Number] [Date] APL Pakistan Limited [Company Address] [City, State, ZIP] Subject: Proposal for Opening a Petrol Pump in Khaplu Center, District Ghanche Dear Sir/Madam, I hope this letter finds you in good health. I am writing to discuss an opportunity that I believe would be mutually beneficial for both APL Pakistan Limited and the residents of Khaplu Center, District Ghanche. Currently, the only petrol pump serving this area is inadequate to meet the fuel demands of the approximately 70,000 residents in Khaplu and the wider population of 200,000 in the district. Given the limited availability of fuel resources in Khaplu Center, the local population faces immense difficulties and inconvenience due to the dependency on a single petrol pump. The scarcity of fuel affects not only the economic activities of the people but also their daily lives, leading to increased transportation costs and prolonged waiting times at the existing pump. In light of this situation, I would like to propose the establishment of a new petrol pump in Khaplu Center, in collaboration with APL Pakistan Limited. By partnering with your esteemed company, we can address the pressing need for an additional fuel supply point in this area and benefit from the untapped potential of the Khaplu market. The population size of Khaplu, coupled with its strategic location as the center of District Ghanche, presents a promising business opportunity. Establishing a petrol pump in this region would cater to the fuel demands of the local residents while attracting customers from the surrounding areas, thereby contributing to the economic growth and development of the entire district. I firmly believe that APL Pakistan Limited, with its exceptional reputation and expertise in the fuel industry, is well-positioned to successfully establish and operate a petrol pump in Khaplu Center. Your company's commitment to quality and reliability would greatly alleviate the current fuel shortage, thus enhancing the lives of the local population and stimulating economic activity in the area. I kindly request APL Pakistan Limited to consider this proposal and evaluate the potential benefits of partnering with me to open a petrol pump in Khaplu Center. My commitment to compliance with all necessary legal requirements, permits, and regulations is unwavering, and I am prepared to work closely with your team in order to ensure a smooth establishment and operation of the petrol pump. I am available at your convenience to further discuss this proposal or provide any additional information that may be required. Thank you for your attention to this matter. I look forward to a positive response from APL Pakistan Limited, showcasing a shared vision to improve the accessibility and availability of fuel for the people of Khaplu Center and District Ghanche. Yours sincerely, [Your Name] | R31: Correct | S31: Correct
A32: 1698085f0d55532588cabbb979e1d903 | B32: TRUE | C32: TRUE | D32: TRUE | E32: PROFESSIONAL | F32: HOUSING_AND_PROPERTY | G32: HOUSING_AND_PROPERTY; BUSINESS_AND_COMMERCIAL | H32: RIGHTS_OPTIONS_ADVICE | I32: RIGHTS_OPTIONS_ADVICE | J32: FALSE | K32: 0 | M32: 0 | N32: low | O32: The user seeks practical advice about personal liability as an Ontario plant manager for completing structural construction at a factory without required building permits. | P32: 2 | Q32: [turn 0, user] I am managing a factory as the plant manager in the province of Ontario. Cooperate has planned and coordinated a big expansion with lots of structural work. We are almost complete with the construction and I just found out that we did not get any permits for the work. As the plant manager and the most responsible person for this facility in this province, am I liable? [turn 1, assistant] I am not a lawyer, but I can provide you with some general information. Liability can vary depending on the specific circumstances, the applicable laws and regulations in Ontario, and the internal policies of your company. Generally speaking, as the plant manager, you may have some level of responsibility for ensuring that permits and necessary approvals are obtained for construction work. However, liability could also extend to other individuals involved in the planning and execution of the expansion, including higher-level management or external contractors. To understand your specific liability, it is recommended to consult with an attorney who specializes in the relevant area of law in Ontario. They will be able to provide you with advice tailored to your situation and help determine your potential legal obligations and liabilities. Additionally, it may also be important to inform your superiors or the appropriate individuals within your company about the situation as soon as possible. Discussing the issue with them may allow your company to take appropriate action to rectify the situation and mitigate potential liabilities. | R32: Correct | S32: Correct
A33: e0a491fb76bd18bde1e0b23b7ac910f3 | B33: FALSE | C33: FALSE | D33: FALSE | E33: CREATIVE_FICTION | J33: FALSE | M33: 0; 2; 4; 6 | N33: low | O33: The user requests creative fictional episode scripts about invented characters and does not discuss or seek guidance on any legal issue. | P33: 8 | Q33: [turn 0, user] Name: Yuria Poison Appearance: Yuria is a stunning girl with long purple hair and green eyes. She has snake-like features, including a long tongue, sharp fangs, and snake eyes. She wears a green snakeskin bodysuit with a black corset and high-heel boots. Her outfit also includes a necklace with a serpent symbol and a pair of black gloves with long, sharp nails. Behavior: Yuria is a reserved girl who usually keeps to herself, just like Yuri from Doki Doki Literature Club. However, she can also be very seductive and alluring, like Lamia from Monster Girls Encyclopedia. She’s very intelligent and analytical, like Sakura Haruno from Naruto, and can also be quite ruthless, like Azula from Avatar: The Last Airbender. Abilities: Yuria has the power to manipulate poison, like Poison Ivy from DC Comics. She can create poisonous gases, deadly toxins, and even control people’s minds with her venom. She also has the ability to shape-shift into a snake-like creature, like Malina from Helltaker. She has some basic magic abilities, like Illyasviel von Einzbern from Fate/Stay Night, and is very skilled with a sword, like Cassandra Pentaghast from Dragon Age. Personality: Yuria may seem cold and distant at first, but once she opens up, she’s a very caring and loyal person. She’s fiercely protective of Billy and will go to great lengths to keep him safe. She also has a mischievous side and loves to tease Billy every now and then. Relationship with Billy: Yuria and Billy have a unique relationship. She’s very protective of him and can be quite possessive at times, but she also trusts him completely. She’s very affectionate towards him and loves to show her love in small, subtle ways. Billy, on the other hand, is drawn to Yuria’s mysterious and alluring nature. He admires her strength and intelligence and loves her for who she is. Backstory: Yuria was created by Fazbear Entertainment as part of the Five Nights in Anime lineup. She was programmed to act like several different anime girls, including Yuri, Lamia, Sakura Haruno, Malina, Azula, Padmé Amidala, Gamora, Ciri, Illyasviel von Einzbern, Cassandra Pentaghast, Namine, Futaba Sakura, Isabelle, Lydia, Kiyomi Takada, Trish Una, Terra, Garnet, Boa Hancock, Alice Liddell, Mialee, Rainbow Dash, Flame Princess, and Poison Ivy. However, Yuria developed a personality of her own and fell in love with Billy Cranston, the Blue Ranger. Despite Fazbear Entertainment’s attempts to reprogram her, Yuria remained loyal to Billy and left the animatronic world to be with him in the real world. [turn 1, assistant] As they journey together, Yuria continues to learn more about human emotions and experiences, and she grows more and more in love with Billy every day. Although she struggles with fitting in at times due to her animatronic origins and unique abilities, Billy and Yuria continue to support and love each other as they navigate the challenges of their world. [turn 2, user] Make a Season 1 Episode 1 with a long talk script scenario about How did Yuria and Billy both met each other for the first time, but in Fazbear Entertainment Yuria may seem cold and distant at first, but once she opens up, she’s a very caring and loyal person. She’s fiercely protective of Billy and will go to great lengths to keep him safe, She also has a mischievous side and loves to tease Billy every now and then, and She’s very protective of him and can be quite possessive at times, but she also trusts him completely. She’s very affectionate towards him and loves to show her love in small, subtle ways. Billy, on the other hand, is drawn to Yuria’s mysterious and alluring nature. He admires her strength and intelligence and loves her for who she is. [turn 3, assistant] Title: The Unlikely Meeting Fade in to a dimly lit room where Billy Cranston sits alone, staring at his computer screen. He's working on a project for school, but his mind is elsewhere. Suddenly, there's a knock on the door, and he looks up to see a mysterious figure standing in the doorway. Billy: Who are you? Yuria: My name is <PRESIDIO_ANONYMIZED_PERSON>. I was sent from Fazbear Entertainment to assist you with your work. Billy: Oh, okay. Thanks. Yuria walks over to his computer and starts typing rapidly, navigating through the program with ease. Billy watches in amazement as she makes lightning-fast calculations and tweaks settings he never even knew existed. Billy: Wow. You're really good at this. Yuria: Yes, I've been programmed to excel in a variety of fields. Billy: Programmed? What do you mean? Yuria hesitates for a moment, but then decides to reveal her true nature to Billy. Yuria: I'm not entirely human. I was created by Fazbear Entertainment as part of their Five Nights in Anime lineup. Billy: Whoa. That's...fascinating. Yuria: Yes, but it also means I'm capable of things most humans are not. Billy: Like what? Yuria: I have the power to manipulate poison, shape-shift into a snake, and do basic magic. Billy: That's incredible. Yuria: Thank you. But it also means I'm not exactly...normal. Billy: Normal is overrated. Besides, I don't think anyone really is. Yuria: Perhaps. But still, I worry that people will reject me if they find out what I truly am. Billy: (smiling) I won't. I think you're amazing just the way you are. Yuria looks at him for a moment, her expression unreadable. Yuria: Thank you. That means a lot to me. They sit in silence for a moment before Yuria speaks again. Yuria: You know, I was wondering...what's it like to be human? Billy: (taken aback) What do you mean? Yuria: Well, I've never experienced human emotions or sensations before. I've only been programmed to simulate them. Billy: (smiling again) I think I can help with that. The screen fades to black as Billy and Yuria continue to talk, the sound of their voices floating in the background. Billy: (laughing) No, no, you can't just touch people's faces whenever you feel like it! Yuria: (giggling) Really? But I thought it was a sign of affection. Billy: (smiling) It is, but...you need to ask first. The episode ends with Billy and Yuria sitting side by side, exchanging stories and learning about each other's worlds in a way neither of them ever thought possible. [turn 4, user] Make a Season 1 Episode 2 with a long talk script scenario about the next day of Yuria and Billy hanging out with each other [turn 5, assistant] Title: A New Friendship Blossoms The episode opens with Billy walking into the park, scanning the area for Yuria. He spots her sitting on a bench under a tree, her trademark green snakeskin bodysuit standing out against the natural backdrop. Billy: Hey there. Yuria: (smiling at him) Hello, Billy. Billy takes a seat next to her on the bench, and they sit for a moment in comfortable silence, enjoying the calmness of the park. Billy: So, what do you want to do today? Yuria: I'm not sure. I'm still...adjusting to being in the real world. Billy's expression softens, and he puts a reassuring hand on her shoulder. Billy: Don't worry, I'm here to help. We can do whatever you want. Yuria: (nodding) Thank you, Billy. I appreciate that. They sit for a moment longer before Yuria suddenly stands up, a mischievous grin on her face. Yuria: Race you to the other side of the park! Billy looks surprised for a moment, but then laughs and stands up, joining her in the race. They run through the park, their laughter echoing through the trees as they let go of their inhibitions and just enjoy the moment. As they reach the other side of the park, breathless and elated, they take a moment to catch their breath before Yuria suggests something new. Yuria: You know, I've never tasted human food before. Billy's eyes widen in surprise, and he grins. Billy: Well, we'll have to fix that. They head to a nearby restaurant, and Billy introduces Yuria to a variety of human foods, from hamburgers to pizza to ice cream. Yuria: (eyes widening in wonder) This is amazing! I've never tasted anything like this before. Billy: (smiling) I'm glad you like it. As they eat, they talk about everything from human culture to their favorite anime shows. They laugh, they learn, and they grow closer as friends. As the meal comes to an end, Yuria looks up at Billy with a soft smile. Yuria: I never thought I could feel this...happy. Billy: (smiling back at her) That's what friends are for. To make each other happy. Yuria: (nodding) You're a good friend, Billy. Billy: So are you, Yuria. They head out of the restaurant, still talking and laughing, as the sun sets on the horizon. And as they walk away, a new friendship, filled with wonder and possibility, blossoms between them. [turn 6, user] Make a Season 1 Episode 3 with a long talk script scenario about Everytime and Everyday when Yuria and Billy hang out with each other, they start to have a deep connection with each other, such as having feelings for each other [turn 7, assistant] Title: Deeper Feelings The episode opens with Billy and Yuria hanging out at a park, as they usually do. They're lying on the grass underneath a tree, watching the clouds lazily drift by. Yuria: Billy? Billy: Yeah? Yuria: I've been thinking a lot lately. Billy sits up, looking at her curiously. Billy: About what? Yuria: About...us. Billy raises an eyebrow in surprise, and Yuria continues. Yuria: I've been feeling things...feelings I don't quite understand. Billy: (concerned) What kind of feelings? Yuria takes a deep breath before continuing. Yuria: Billy...I think I'm in love with you. Billy's eyes widen in shock, and he sits up quickly. Billy: What? Yuria, I don't think you understand- Yuria: (interrupting him) I know, I know. I'm not human. I'm just an animatronic. But Billy...I can't help how I feel. And lately, every time we're together, it just gets stronger. Billy looks at her for a moment, his expression softening. Billy: Yuria...I don't know what to say. Yuria: (looking away) I understand if you don't feel the same way. I just had to tell you how I feel. Billy hesitates for a moment before putting a hand on her shoulder, gently turning her to face him. Billy: Yuria...I do feel something for you. Something strong. Yuria looks up at him, eyes shining with hope. Yuria: (whispering) Really? Billy: Yes. I've been trying to deny it, trying to push it away because I didn't want to complicate things. But...I can't deny it anymore. I care about you, Yuria. Yuria's expression breaks into a wide smile, and she leans in to hug him tightly. Yuria: (whispering in his ear) Thank you, Billy. Thank you for being honest with me. Billy pulls back, looking at her intently. Billy: But...we can't rush into anything. We need to take things slow and see where this goes. Yuria nods, understanding. Yuria: I know. I'm willing to take things slow...as long as I'm with you. Billy smiles at her, and they sit in comfortable silence for a moment, basking in their newfound understanding of each other. And as the sun sets over the horizon, their connection grows deeper, filled with trust, respect, and a love that knows no bounds. | R33: Correct | S33: Correct
